Subtractors/paraller_subtractor/full_subtractor.v
module full_subtractor(
input A, B, C,
output Sub, Borrow
);

wire x1, n1, n2, n3;

xor(Sub, A, B, C);

not(n1, A);
and(n2, n1, B);
and(n3, n1, C);
and(x1, B, C);

or(Borrow, n2, n3, x1);
endmodule

Subtractors/full_subtractor/full_subtractor_tb.v
module full_subtractor_tb;

reg a,b,c;
wire sub,borrow;
integer i;

full_subtractor dut(
.A(a),
.B(b),
.C(c),
.Sub(sub),
.Borrow(borrow)
);

initial begin
$dumpfile("full_subtractor.vcd");
$dumpvars(0,full_subtractor_tb);

for(i=0;i<8;i=i+1) begin
    {a,b,c}=i;
    #10;
end

$finish;
end

initial begin
$monitor("A=%b,B=%b,C=%b,Sub=%b,Borrow=%b",
          a,b,c,sub,borrow);
end

endmodule

Subtractors/full_subtractor/full_subtractor.vcd
$date
	Fri Jun 19 05:42:30 2026
$end
$version
	Icarus Verilog
$end
$timescale
	1s
$end
$scope module full_subtractor_tb $end
$var wire 1 ! sub $end
$var wire 1 " borrow $end
$var reg 1 # a $end
$var reg 1 $ b $end
$var reg 1 % c $end
$var integer 32 & i [31:0] $end
$scope module dut $end
$var wire 1 # A $end
$var wire 1 $ B $end
$var wire 1 " Borrow $end
$var wire 1 % C $end
$var wire 1 ! Sub $end
$var wire 1 ' n1 $end
$var wire 1 ( n2 $end
$var wire 1 ) n3 $end
$var wire 1 * x1 $end
$upscope $end
$upscope $end
$enddefinitions $end
$comment Show the parameter values. $end
$dumpall
$end
#0
$dumpvars
0*
0)
0(
1'
b0 &
0%
0$
0#
0"
0!
$end
#10
1"
1!
1)
1%
b1 &
#20
1(
0)
1$
0%
b10 &
#30
0!
1)
1*
1%
b11 &
#40
0"
0'
0(
1!
0)
0*
1#
0$
0%
b100 &
#50
0!
1%
b101 &
#60
1$
0%
b110 &
#70
1"
1!
1*
1%
b111 &
#80
b1000 &
