Subtractors/paraller_subtractor/full_subtractor.v
module full_subtractor(
input A, B, C,
output Sub, Borrow
);

wire x1, n1, n2, n3;

xor(Sub, A, B, C);

not(n1, A);
and(n2, n1, B);
and(n3, n1, C);
and(x1, B, C);

or(Borrow, n2, n3, x1);
endmodule

Subtractors/paraller_subtractor/paraller_subtractor.v
module paraller_subtractor(
input [3:0] A,B,
input Bin,
output [3:0]D,
output Bout);

wire B0, B1, B2;

full_subtractor FS0(
    .A(A[0]),
    .B(B[0]),
    .C(Bin),
    .Sub(D[0]),
    .Borrow(B0)
);

full_subtractor FS1(
    .A(A[1]),
    .B(B[1]),
    .C(B0),
    .Sub(D[1]),
    .Borrow(B1)
);

full_subtractor FS2(
    .A(A[2]),
    .B(B[2]),
    .C(B1),
    .Sub(D[2]),
    .Borrow(B2)
);

full_subtractor FS3(
    .A(A[3]),
    .B(B[3]),
    .C(B2),
    .Sub(D[3]),
    .Borrow(Bout)
);
endmodule

Subtractors/paraller_subtractor/paraller_subtractor_tb.v
module paraller_subtractor_tb;

reg [3:0] A,B;
reg Bin;
wire [3:0] D;
wire Bout;

integer i,j,k;

paraller_subtractor dut(
.A(A),
.B(B),
.Bin(Bin),
.D(D),
.Bout(Bout)
);

initial begin
    $dumpfile("paraller_subtractor.vcd");
    $dumpvars(0,paraller_subtractor_tb);

    for(k=0; k<2; k=k+1) begin
        Bin=k;
        for(i=0; i<16; i=i+1) begin
            for(j=0; j<16; j=j+1) begin
                A=i;
                B=j;
                #10;
            end
        end
    end

    $finish;
end

initial begin
    $monitor("A=%h B=%h Bin=%b D=%h Bout=%b",
              A,B,Bin,D,Bout);
end

endmodule

Subtractors/paraller_subtractor/paraller_subtractor.vcd
$date
	Mon Jun 22 05:00:36 2026
$end
$version
	Icarus Verilog
$end
$timescale
	1s
$end
$scope module paraller_subtractor_tb $end
$var wire 4 ! D [3:0] $end
$var wire 1 " Bout $end
$var reg 4 # A [3:0] $end
$var reg 4 $ B [3:0] $end
$var reg 1 % Bin $end
$var integer 32 & i [31:0] $end
$var integer 32 ' j [31:0] $end
$var integer 32 ( k [31:0] $end
$scope module dut $end
$var wire 4 ) A [3:0] $end
$var wire 4 * B [3:0] $end
$var wire 1 % Bin $end
$var wire 4 + D [3:0] $end
$var wire 1 " Bout $end
$var wire 1 , B2 $end
$var wire 1 - B1 $end
$var wire 1 . B0 $end
$scope module FS0 $end
$var wire 1 / A $end
$var wire 1 0 B $end
$var wire 1 . Borrow $end
$var wire 1 % C $end
$var wire 1 1 Sub $end
$var wire 1 2 n1 $end
$var wire 1 3 n2 $end
$var wire 1 4 n3 $end
$var wire 1 5 x1 $end
$upscope $end
$scope module FS1 $end
$var wire 1 6 A $end
$var wire 1 7 B $end
$var wire 1 - Borrow $end
$var wire 1 . C $end
$var wire 1 8 Sub $end
$var wire 1 9 n1 $end
$var wire 1 : n2 $end
$var wire 1 ; n3 $end
$var wire 1 < x1 $end
$upscope $end
$scope module FS2 $end
$var wire 1 = A $end
$var wire 1 > B $end
$var wire 1 , Borrow $end
$var wire 1 - C $end
$var wire 1 ? Sub $end
$var wire 1 @ n1 $end
$var wire 1 A n2 $end
$var wire 1 B n3 $end
$var wire 1 C x1 $end
$upscope $end
$scope module FS3 $end
$var wire 1 D A $end
$var wire 1 E B $end
$var wire 1 " Borrow $end
$var wire 1 , C $end
$var wire 1 F Sub $end
$var wire 1 G n1 $end
$var wire 1 H n2 $end
$var wire 1 I n3 $end
$var wire 1 J x1 $end
$upscope $end
$upscope $end
$upscope $end
$enddefinitions $end
$comment Show the parameter values. $end
$dumpall
$end
#0
$dumpvars
0J
0I
0H
1G
0F
0E
0D
0C
0B
0A
1@
0?
0>
0=
0<
0;
0:
19
08
07
06
05
04
03
12
01
00
0/
0.
0-
0,
b0 +
b0 *
b0 )
b0 (
b0 '
b0 &
0%
b0 $
b0 #
0"
b0 !
$end
#10
1"
1F
1I
1,
1?
1B
1-
18
1;
1.
b1111 !
b1111 +
11
13
10
b1 $
b1 *
b1 '
#20
0;
0.
01
03
b1110 !
b1110 +
18
1:
0<
00
17
b10 $
b10 *
b10 '
#30
08
1;
1<
1.
b1101 !
b1101 +
11
13
10
b11 $
b11 *
b11 '
#40
0B
0-
0;
0.
01
03
08
0:
0<
b1100 !
b1100 +
1?
1A
0C
00
07
1>
b100 $
b100 *
b100 '
#50
0?
1B
1C
1-
18
1;
1.
b1011 !
b1011 +
11
13
10
b101 $
b101 *
b101 '
#60
0;
0.
01
03
b1010 !
b1010 +
18
1:
0<
00
17
b110 $
b110 *
b110 '
#70
08
1;
1<
1.
b1001 !
b1001 +
11
13
10
b111 $
b111 *
b111 '
#80
0I
0,
0B
0-
0;
0.
01
03
08
0:
0<
0?
0A
0C
b1000 !
b1000 +
1F
1H
0J
00
07
0>
1E
b1000 $
b1000 *
b1000 '
#90
0F
1I
1J
1,
1?
1B
1-
18
1;
1.
b111 !
b111 +
11
13
10
b1001 $
b1001 *
b1001 '
#100
0;
0.
01
03
b110 !
b110 +
18
1:
0<
00
17
b1010 $
b1010 *
b1010 '
#110
08
1;
1<
1.
b101 !
b101 +
11
13
10
b1011 $
b1011 *
b1011 '
#120
0B
0-
0;
0.
01
03
08
0:
0<
b100 !
b100 +
1?
1A
0C
00
07
1>
b1100 $
b1100 *
b1100 '
#130
0?
1B
1C
1-
18
1;
1.
b11 !
b11 +
11
13
10
b1101 $
b1101 *
b1101 '
#140
0;
0.
01
03
b10 !
b10 +
18
1:
0<
00
17
b1110 $
b1110 *
b1110 '
#150
08
1;
1<
1.
b1 !
b1 +
11
13
10
b1111 $
b1111 *
b1111 '
#160
0"
0I
0,
0B
0-
0;
0.
03
08
0:
0<
0?
0A
0C
b1 !
b1 +
0F
0H
0J
02
00
07
0>
0E
1/
b0 $
b0 *
b1 #
b1 )
b1 &
b0 '
#170
b0 !
b0 +
01
10
b1 $
b1 *
b1 '
#180
1"
1F
1I
1,
1?
1B
1-
11
b1111 !
b1111 +
18
1:
00
17
b10 $
b10 *
b10 '
#190
b1110 !
b1110 +
01
10
b11 $
b11 *
b11 '
#200
0B
0-
11
08
0:
b1101 !
b1101 +
1?
1A
0C
00
07
1>
b100 $
b100 *
b100 '
#210
b1100 !
b1100 +
01
10
b101 $
b101 *
b101 '
#220
0?
1B
1C
1-
11
b1011 !
b1011 +
18
1:
00
17
b110 $
b110 *
b110 '
#230
b1010 !
b1010 +
01
10
b111 $
b111 *
b111 '
#240
0I
0,
0B
0-
11
08
0:
0?
0A
0C
b1001 !
b1001 +
1F
1H
0J
00
07
0>
1E
b1000 $
b1000 *
b1000 '
#250
b1000 !
b1000 +
01
10
b1001 $
b1001 *
b1001 '
#260
0F
1I
1J
1,
1?
1B
1-
11
b111 !
b111 +
18
1:
00
17
b1010 $
b1010 *
b1010 '
#270
b110 !
b110 +
01
10
b1011 $
b1011 *
b1011 '
#280
0B
0-
11
08
0:
b101 !
b101 +
1?
1A
0C
00
07
1>
b1100 $
b1100 *
b1100 '
#290
b100 !
b100 +
01
10
b1101 $
b1101 *
b1101 '
#300
0?
1B
1C
1-
11
b11 !
b11 +
18
1:
00
17
b1110 $
b1110 *
b1110 '
#310
b10 !
b10 +
01
10
b1111 $
b1111 *
b1111 '
#320
0"
0I
0,
0B
0-
0:
0?
0A
0C
b10 !
b10 +
0F
0H
0J
12
09
00
07
0>
0E
0/
16
b0 $
b0 *
b10 #
b10 )
b10 &
b0 '
#330
08
1.
b1 !
b1 +
11
13
10
b1 $
b1 *
b1 '
#340
0"
0F
0I
0,
0?
0B
0.
0-
01
03
b0 !
b0 +
08
0<
00
17
b10 $
b10 *
b10 '
#350
1"
1F
1I
1,
1?
1B
1-
18
1<
1.
b1111 !
b1111 +
11
13
10
b11 $
b11 *
b11 '
#360
0B
0.
0-
01
03
18
0<
b1110 !
b1110 +
1?
1A
0C
00
07
1>
b100 $
b100 *
b100 '
#370
08
1.
b1101 !
b1101 +
11
13
10
b101 $
b101 *
b101 '
#380
1?
0B
0C
0.
0-
01
03
b1100 !
b1100 +
08
0<
00
17
b110 $
b110 *
b110 '
#390
0?
1B
1C
1-
18
1<
1.
b1011 !
b1011 +
11
13
10
b111 $
b111 *
b111 '
#400
0I
0,
0B
0.
0-
01
03
18
0<
0?
0A
0C
b1010 !
b1010 +
1F
1H
0J
00
07
0>
1E
b1000 $
b1000 *
b1000 '
#410
08
1.
b1001 !
b1001 +
11
13
10
b1001 $
b1001 *
b1001 '
#420
1F
0I
0J
0,
0?
0B
0.
0-
01
03
b1000 !
b1000 +
08
0<
00
17
b1010 $
b1010 *
b1010 '
#430
0F
1I
1J
1,
1?
1B
1-
18
1<
1.
b111 !
b111 +
11
13
10
b1011 $
b1011 *
b1011 '
#440
0B
0.
0-
01
03
18
0<
b110 !
b110 +
1?
1A
0C
00
07
1>
b1100 $
b1100 *
b1100 '
#450
08
1.
b101 !
b101 +
11
13
10
b1101 $
b1101 *
b1101 '
#460
1?
0B
0C
0.
0-
01
03
b100 !
b100 +
08
0<
00
17
b1110 $
b1110 *
b1110 '
#470
0?
1B
1C
1-
18
1<
1.
b11 !
b11 +
11
13
10
b1111 $
b1111 *
b1111 '
#480
0"
0I
0,
0B
0.
0-
03
18
0<
0?
0A
0C
b11 !
b11 +
0F
0H
0J
02
00
07
0>
0E
1/
b0 $
b0 *
b11 #
b11 )
b11 &
b0 '
#490
b10 !
b10 +
01
10
b1 $
b1 *
b1 '
#500
11
b1 !
b1 +
08
00
17
b10 $
b10 *
b10 '
#510
b0 !
b0 +
01
10
b11 $
b11 *
b11 '
#520
1"
1F
1I
1,
11
18
b1111 !
b1111 +
1?
1A
00
07
1>
b100 $
b100 *
b100 '
#530
b1110 !
b1110 +
01
10
b101 $
b101 *
b101 '
#540
11
b1101 !
b1101 +
08
00
17
b110 $
b110 *
b110 '
#550
b1100 !
b1100 +
01
10
b111 $
b111 *
b111 '
#560
0I
0,
11
18
0?
0A
b1011 !
b1011 +
1F
1H
0J
00
07
0>
1E
b1000 $
b1000 *
b1000 '
#570
b1010 !
b1010 +
01
10
b1001 $
b1001 *
b1001 '
#580
11
b1001 !
b1001 +
08
00
17
b1010 $
b1010 *
b1010 '
#590
b1000 !
b1000 +
01
10
b1011 $
b1011 *
b1011 '
#600
0F
1I
1J
1,
11
18
b111 !
b111 +
1?
1A
00
07
1>
b1100 $
b1100 *
b1100 '
#610
b110 !
b110 +
01
10
b1101 $
b1101 *
b1101 '
#620
11
b101 !
b101 +
08
00
17
b1110 $
b1110 *
b1110 '
#630
b100 !
b100 +
01
10
b1111 $
b1111 *
b1111 '
#640
0"
0I
0,
0A
b100 !
b100 +
0F
0H
0J
12
19
0@
00
07
0>
0E
0/
06
1=
b0 $
b0 *
b100 #
b100 )
b100 &
b0 '
#650
0?
1-
18
1;
1.
b11 !
b11 +
11
13
10
b1 $
b1 *
b1 '
#660
0;
0.
01
03
b10 !
b10 +
18
1:
0<
00
17
b10 $
b10 *
b10 '
#670
08
1;
1<
1.
b1 !
b1 +
11
13
10
b11 $
b11 *
b11 '
#680
0-
0"
0;
0F
0I
0.
0,
01
03
08
0:
0<
b0 !
b0 +
0?
0C
00
07
1>
b100 $
b100 *
b100 '
#690
1"
1F
1I
1,
1?
1C
1-
18
1;
1.
b1111 !
b1111 +
11
13
10
b101 $
b101 *
b101 '
#700
0;
0.
01
03
b1110 !
b1110 +
18
1:
0<
00
17
b110 $
b110 *
b110 '
#710
08
1;
1<
1.
b1101 !
b1101 +
11
13
10
b111 $
b111 *
b111 '
#720
0-
0;
0I
0.
0,
01
03
08
0:
0<
1?
0C
b1100 !
b1100 +
1F
1H
0J
00
07
0>
1E
b1000 $
b1000 *
b1000 '
#730
0?
1-
18
1;
1.
b1011 !
b1011 +
11
13
10
b1001 $
b1001 *
b1001 '
#740
0;
0.
01
03
b1010 !
b1010 +
18
1:
0<
00
17
b1010 $
b1010 *
b1010 '
#750
08
1;
1<
1.
b1001 !
b1001 +
11
13
10
b1011 $
b1011 *
b1011 '
#760
0-
0;
1F
0I
0J
0.
0,
01
03
08
0:
0<
b1000 !
b1000 +
0?
0C
00
07
1>
b1100 $
b1100 *
b1100 '
#770
0F
1I
1J
1,
1?
1C
1-
18
1;
1.
b111 !
b111 +
11
13
10
b1101 $
b1101 *
b1101 '
#780
0;
0.
01
03
b110 !
b110 +
18
1:
0<
00
17
b1110 $
b1110 *
b1110 '
#790
08
1;
1<
1.
b101 !
b101 +
11
13
10
b1111 $
b1111 *
b1111 '
#800
0-
0"
0;
0I
0.
0,
03
08
0:
0<
1?
0C
b101 !
b101 +
0F
0H
0J
02
00
07
0>
0E
1/
b0 $
b0 *
b101 #
b101 )
b101 &
b0 '
#810
b100 !
b100 +
01
10
b1 $
b1 *
b1 '
#820
0?
1-
11
b11 !
b11 +
18
1:
00
17
b10 $
b10 *
b10 '
#830
b10 !
b10 +
01
10
b11 $
b11 *
b11 '
#840
0"
0F
0I
0-
0,
11
08
0:
b1 !
b1 +
0?
0C
00
07
1>
b100 $
b100 *
b100 '
#850
b0 !
b0 +
01
10
b101 $
b101 *
b101 '
#860
1"
1F
1I
1,
1?
1C
1-
11
b1111 !
b1111 +
18
1:
00
17
b110 $
b110 *
b110 '
#870
b1110 !
b1110 +
01
10
b111 $
b111 *
b111 '
#880
0I
0-
0,
11
08
0:
1?
0C
b1101 !
b1101 +
1F
1H
0J
00
07
0>
1E
b1000 $
b1000 *
b1000 '
#890
b1100 !
b1100 +
01
10
b1001 $
b1001 *
b1001 '
#900
0?
1-
11
b1011 !
b1011 +
18
1:
00
17
b1010 $
b1010 *
b1010 '
#910
b1010 !
b1010 +
01
10
b1011 $
b1011 *
b1011 '
#920
1F
0I
0J
0-
0,
11
08
0:
b1001 !
b1001 +
0?
0C
00
07
1>
b1100 $
b1100 *
b1100 '
#930
b1000 !
b1000 +
01
10
b1101 $
b1101 *
b1101 '
#940
0F
1I
1J
1,
1?
1C
1-
11
b111 !
b111 +
18
1:
00
17
b1110 $
b1110 *
b1110 '
#950
b110 !
b110 +
01
10
b1111 $
b1111 *
b1111 '
#960
0"
0I
0-
0,
0:
1?
0C
b110 !
b110 +
0F
0H
0J
12
09
00
07
0>
0E
0/
16
b0 $
b0 *
b110 #
b110 )
b110 &
b0 '
#970
08
1.
b101 !
b101 +
11
13
10
b1 $
b1 *
b1 '
#980
1?
0.
0-
01
03
b100 !
b100 +
08
0<
00
17
b10 $
b10 *
b10 '
#990
0?
1-
18
1<
1.
b11 !
b11 +
11
13
10
b11 $
b11 *
b11 '
#1000
0"
0F
0I
0.
0-
0,
01
03
18
0<
b10 !
b10 +
0?
0C
00
07
1>
b100 $
b100 *
b100 '
#1010
08
1.
b1 !
b1 +
11
13
10
b101 $
b101 *
b101 '
#1020
0"
0F
0I
0,
0?
0C
0.
0-
01
03
b0 !
b0 +
08
0<
00
17
b110 $
b110 *
b110 '
#1030
1"
1F
1I
1,
1?
1C
1-
18
1<
1.
b1111 !
b1111 +
11
13
10
b111 $
b111 *
b111 '
#1040
0I
0.
0-
0,
01
03
18
0<
1?
0C
b1110 !
b1110 +
1F
1H
0J
00
07
0>
1E
b1000 $
b1000 *
b1000 '
#1050
08
1.
b1101 !
b1101 +
11
13
10
b1001 $
b1001 *
b1001 '
#1060
1?
0.
0-
01
03
b1100 !
b1100 +
08
0<
00
17
b1010 $
b1010 *
b1010 '
#1070
0?
1-
18
1<
1.
b1011 !
b1011 +
11
13
10
b1011 $
b1011 *
b1011 '
#1080
1F
0I
0J
0.
0-
0,
01
03
18
0<
b1010 !
b1010 +
0?
0C
00
07
1>
b1100 $
b1100 *
b1100 '
#1090
08
1.
b1001 !
b1001 +
11
13
10
b1101 $
b1101 *
b1101 '
#1100
1F
0I
0J
0,
0?
0C
0.
0-
01
03
b1000 !
b1000 +
08
0<
00
17
b1110 $
b1110 *
b1110 '
#1110
0F
1I
1J
1,
1?
1C
1-
18
1<
1.
b111 !
b111 +
11
13
10
b1111 $
b1111 *
b1111 '
#1120
0"
0I
0.
0-
0,
03
18
0<
1?
0C
b111 !
b111 +
0F
0H
0J
02
00
07
0>
0E
1/
b0 $
b0 *
b111 #
b111 )
b111 &
b0 '
#1130
b110 !
b110 +
01
10
b1 $
b1 *
b1 '
#1140
11
b101 !
b101 +
08
00
17
b10 $
b10 *
b10 '
#1150
b100 !
b100 +
01
10
b11 $
b11 *
b11 '
#1160
11
18
b11 !
b11 +
0?
00
07
1>
b100 $
b100 *
b100 '
#1170
b10 !
b10 +
01
10
b101 $
b101 *
b101 '
#1180
11
b1 !
b1 +
08
00
17
b110 $
b110 *
b110 '
#1190
b0 !
b0 +
01
10
b111 $
b111 *
b111 '
#1200
1"
11
18
1?
b1111 !
b1111 +
1F
1H
00
07
0>
1E
b1000 $
b1000 *
b1000 '
#1210
b1110 !
b1110 +
01
10
b1001 $
b1001 *
b1001 '
#1220
11
b1101 !
b1101 +
08
00
17
b1010 $
b1010 *
b1010 '
#1230
b1100 !
b1100 +
01
10
b1011 $
b1011 *
b1011 '
#1240
11
18
b1011 !
b1011 +
0?
00
07
1>
b1100 $
b1100 *
b1100 '
#1250
b1010 !
b1010 +
01
10
b1101 $
b1101 *
b1101 '
#1260
11
b1001 !
b1001 +
08
00
17
b1110 $
b1110 *
b1110 '
#1270
b1000 !
b1000 +
01
10
b1111 $
b1111 *
b1111 '
#1280
0"
0H
12
19
1@
0G
00
07
0>
0E
0/
06
0=
1D
b0 $
b0 *
b1000 #
b1000 )
b1000 &
b0 '
#1290
0F
1,
1?
1B
1-
18
1;
1.
b111 !
b111 +
11
13
10
b1 $
b1 *
b1 '
#1300
0;
0.
01
03
b110 !
b110 +
18
1:
0<
00
17
b10 $
b10 *
b10 '
#1310
08
1;
1<
1.
b101 !
b101 +
11
13
10
b11 $
b11 *
b11 '
#1320
0B
0-
0;
0.
01
03
08
0:
0<
b100 !
b100 +
1?
1A
0C
00
07
1>
b100 $
b100 *
b100 '
#1330
0?
1B
1C
1-
18
1;
1.
b11 !
b11 +
11
13
10
b101 $
b101 *
b101 '
#1340
0;
0.
01
03
b10 !
b10 +
18
1:
0<
00
17
b110 $
b110 *
b110 '
#1350
08
1;
1<
1.
b1 !
b1 +
11
13
10
b111 $
b111 *
b111 '
#1360
0,
0B
0-
0;
0.
0"
01
03
08
0:
0<
0?
0A
0C
b0 !
b0 +
0F
0J
00
07
0>
1E
b1000 $
b1000 *
b1000 '
#1370
1"
1F
1J
1,
1?
1B
1-
18
1;
1.
b1111 !
b1111 +
11
13
10
b1001 $
b1001 *
b1001 '
#1380
0;
0.
01
03
b1110 !
b1110 +
18
1:
0<
00
17
b1010 $
b1010 *
b1010 '
#1390
08
1;
1<
1.
b1101 !
b1101 +
11
13
10
b1011 $
b1011 *
b1011 '
#1400
0B
0-
0;
0.
01
03
08
0:
0<
b1100 !
b1100 +
1?
1A
0C
00
07
1>
b1100 $
b1100 *
b1100 '
#1410
0?
1B
1C
1-
18
1;
1.
b1011 !
b1011 +
11
13
10
b1101 $
b1101 *
b1101 '
#1420
0;
0.
01
03
b1010 !
b1010 +
18
1:
0<
00
17
b1110 $
b1110 *
b1110 '
#1430
08
1;
1<
1.
b1001 !
b1001 +
11
13
10
b1111 $
b1111 *
b1111 '
#1440
0,
0B
0-
0;
0.
0"
03
08
0:
0<
0?
0A
0C
b1001 !
b1001 +
1F
0J
02
00
07
0>
0E
1/
b0 $
b0 *
b1001 #
b1001 )
b1001 &
b0 '
#1450
b1000 !
b1000 +
01
10
b1 $
b1 *
b1 '
#1460
0F
1,
1?
1B
1-
11
b111 !
b111 +
18
1:
00
17
b10 $
b10 *
b10 '
#1470
b110 !
b110 +
01
10
b11 $
b11 *
b11 '
#1480
0B
0-
11
08
0:
b101 !
b101 +
1?
1A
0C
00
07
1>
b100 $
b100 *
b100 '
#1490
b100 !
b100 +
01
10
b101 $
b101 *
b101 '
#1500
0?
1B
1C
1-
11
b11 !
b11 +
18
1:
00
17
b110 $
b110 *
b110 '
#1510
b10 !
b10 +
01
10
b111 $
b111 *
b111 '
#1520
0,
0B
0-
0"
11
08
0:
0?
0A
0C
b1 !
b1 +
0F
0J
00
07
0>
1E
b1000 $
b1000 *
b1000 '
#1530
b0 !
b0 +
01
10
b1001 $
b1001 *
b1001 '
#1540
1"
1F
1J
1,
1?
1B
1-
11
b1111 !
b1111 +
18
1:
00
17
b1010 $
b1010 *
b1010 '
#1550
b1110 !
b1110 +
01
10
b1011 $
b1011 *
b1011 '
#1560
0B
0-
11
08
0:
b1101 !
b1101 +
1?
1A
0C
00
07
1>
b1100 $
b1100 *
b1100 '
#1570
b1100 !
b1100 +
01
10
b1101 $
b1101 *
b1101 '
#1580
0?
1B
1C
1-
11
b1011 !
b1011 +
18
1:
00
17
b1110 $
b1110 *
b1110 '
#1590
b1010 !
b1010 +
01
10
b1111 $
b1111 *
b1111 '
#1600
0,
0B
0-
0"
0:
0?
0A
0C
b1010 !
b1010 +
1F
0J
12
09
00
07
0>
0E
0/
16
b0 $
b0 *
b1010 #
b1010 )
b1010 &
b0 '
#1610
08
1.
b1001 !
b1001 +
11
13
10
b1 $
b1 *
b1 '
#1620
1F
0,
0?
0B
0.
0-
01
03
b1000 !
b1000 +
08
0<
00
17
b10 $
b10 *
b10 '
#1630
0F
1,
1?
1B
1-
18
1<
1.
b111 !
b111 +
11
13
10
b11 $
b11 *
b11 '
#1640
0B
0.
0-
01
03
18
0<
b110 !
b110 +
1?
1A
0C
00
07
1>
b100 $
b100 *
b100 '
#1650
08
1.
b101 !
b101 +
11
13
10
b101 $
b101 *
b101 '
#1660
1?
0B
0C
0.
0-
01
03
b100 !
b100 +
08
0<
00
17
b110 $
b110 *
b110 '
#1670
0?
1B
1C
1-
18
1<
1.
b11 !
b11 +
11
13
10
b111 $
b111 *
b111 '
#1680
0,
0B
0.
0-
0"
01
03
18
0<
0?
0A
0C
b10 !
b10 +
0F
0J
00
07
0>
1E
b1000 $
b1000 *
b1000 '
#1690
08
1.
b1 !
b1 +
11
13
10
b1001 $
b1001 *
b1001 '
#1700
0"
0F
0J
0,
0?
0B
0.
0-
01
03
b0 !
b0 +
08
0<
00
17
b1010 $
b1010 *
b1010 '
#1710
1"
1F
1J
1,
1?
1B
1-
18
1<
1.
b1111 !
b1111 +
11
13
10
b1011 $
b1011 *
b1011 '
#1720
0B
0.
0-
01
03
18
0<
b1110 !
b1110 +
1?
1A
0C
00
07
1>
b1100 $
b1100 *
b1100 '
#1730
08
1.
b1101 !
b1101 +
11
13
10
b1101 $
b1101 *
b1101 '
#1740
1?
0B
0C
0.
0-
01
03
b1100 !
b1100 +
08
0<
00
17
b1110 $
b1110 *
b1110 '
#1750
0?
1B
1C
1-
18
1<
1.
b1011 !
b1011 +
11
13
10
b1111 $
b1111 *
b1111 '
#1760
0,
0B
0.
0-
0"
03
18
0<
0?
0A
0C
b1011 !
b1011 +
1F
0J
02
00
07
0>
0E
1/
b0 $
b0 *
b1011 #
b1011 )
b1011 &
b0 '
#1770
b1010 !
b1010 +
01
10
b1 $
b1 *
b1 '
#1780
11
b1001 !
b1001 +
08
00
17
b10 $
b10 *
b10 '
#1790
b1000 !
b1000 +
01
10
b11 $
b11 *
b11 '
#1800
0F
1,
11
18
b111 !
b111 +
1?
1A
00
07
1>
b100 $
b100 *
b100 '
#1810
b110 !
b110 +
01
10
b101 $
b101 *
b101 '
#1820
11
b101 !
b101 +
08
00
17
b110 $
b110 *
b110 '
#1830
b100 !
b100 +
01
10
b111 $
b111 *
b111 '
#1840
0,
0"
11
18
0?
0A
b11 !
b11 +
0F
0J
00
07
0>
1E
b1000 $
b1000 *
b1000 '
#1850
b10 !
b10 +
01
10
b1001 $
b1001 *
b1001 '
#1860
11
b1 !
b1 +
08
00
17
b1010 $
b1010 *
b1010 '
#1870
b0 !
b0 +
01
10
b1011 $
b1011 *
b1011 '
#1880
1"
1F
1J
1,
11
18
b1111 !
b1111 +
1?
1A
00
07
1>
b1100 $
b1100 *
b1100 '
#1890
b1110 !
b1110 +
01
10
b1101 $
b1101 *
b1101 '
#1900
11
b1101 !
b1101 +
08
00
17
b1110 $
b1110 *
b1110 '
#1910
b1100 !
b1100 +
01
10
b1111 $
b1111 *
b1111 '
#1920
0,
0"
0A
b1100 !
b1100 +
1F
0J
12
19
0@
00
07
0>
0E
0/
06
1=
b0 $
b0 *
b1100 #
b1100 )
b1100 &
b0 '
#1930
0?
1-
18
1;
1.
b1011 !
b1011 +
11
13
10
b1 $
b1 *
b1 '
#1940
0;
0.
01
03
b1010 !
b1010 +
18
1:
0<
00
17
b10 $
b10 *
b10 '
#1950
08
1;
1<
1.
b1001 !
b1001 +
11
13
10
b11 $
b11 *
b11 '
#1960
0-
0;
1F
0.
0,
01
03
08
0:
0<
b1000 !
b1000 +
0?
0C
00
07
1>
b100 $
b100 *
b100 '
#1970
0F
1,
1?
1C
1-
18
1;
1.
b111 !
b111 +
11
13
10
b101 $
b101 *
b101 '
#1980
0;
0.
01
03
b110 !
b110 +
18
1:
0<
00
17
b110 $
b110 *
b110 '
#1990
08
1;
1<
1.
b101 !
b101 +
11
13
10
b111 $
b111 *
b111 '
#2000
0-
0;
0.
0,
0"
01
03
08
0:
0<
1?
0C
b100 !
b100 +
0F
0J
00
07
0>
1E
b1000 $
b1000 *
b1000 '
#2010
0?
1-
18
1;
1.
b11 !
b11 +
11
13
10
b1001 $
b1001 *
b1001 '
#2020
0;
0.
01
03
b10 !
b10 +
18
1:
0<
00
17
b1010 $
b1010 *
b1010 '
#2030
08
1;
1<
1.
b1 !
b1 +
11
13
10
b1011 $
b1011 *
b1011 '
#2040
0-
0"
0;
0F
0J
0.
0,
01
03
08
0:
0<
b0 !
b0 +
0?
0C
00
07
1>
b1100 $
b1100 *
b1100 '
#2050
1"
1F
1J
1,
1?
1C
1-
18
1;
1.
b1111 !
b1111 +
11
13
10
b1101 $
b1101 *
b1101 '
#2060
0;
0.
01
03
b1110 !
b1110 +
18
1:
0<
00
17
b1110 $
b1110 *
b1110 '
#2070
08
1;
1<
1.
b1101 !
b1101 +
11
13
10
b1111 $
b1111 *
b1111 '
#2080
0-
0;
0.
0,
0"
03
08
0:
0<
1?
0C
b1101 !
b1101 +
1F
0J
02
00
07
0>
0E
1/
b0 $
b0 *
b1101 #
b1101 )
b1101 &
b0 '
#2090
b1100 !
b1100 +
01
10
b1 $
b1 *
b1 '
#2100
0?
1-
11
b1011 !
b1011 +
18
1:
00
17
b10 $
b10 *
b10 '
#2110
b1010 !
b1010 +
01
10
b11 $
b11 *
b11 '
#2120
1F
0-
0,
11
08
0:
b1001 !
b1001 +
0?
0C
00
07
1>
b100 $
b100 *
b100 '
#2130
b1000 !
b1000 +
01
10
b101 $
b101 *
b101 '
#2140
0F
1,
1?
1C
1-
11
b111 !
b111 +
18
1:
00
17
b110 $
b110 *
b110 '
#2150
b110 !
b110 +
01
10
b111 $
b111 *
b111 '
#2160
0-
0,
0"
11
08
0:
1?
0C
b101 !
b101 +
0F
0J
00
07
0>
1E
b1000 $
b1000 *
b1000 '
#2170
b100 !
b100 +
01
10
b1001 $
b1001 *
b1001 '
#2180
0?
1-
11
b11 !
b11 +
18
1:
00
17
b1010 $
b1010 *
b1010 '
#2190
b10 !
b10 +
01
10
b1011 $
b1011 *
b1011 '
#2200
0"
0F
0J
0-
0,
11
08
0:
b1 !
b1 +
0?
0C
00
07
1>
b1100 $
b1100 *
b1100 '
#2210
b0 !
b0 +
01
10
b1101 $
b1101 *
b1101 '
#2220
1"
1F
1J
1,
1?
1C
1-
11
b1111 !
b1111 +
18
1:
00
17
b1110 $
b1110 *
b1110 '
#2230
b1110 !
b1110 +
01
10
b1111 $
b1111 *
b1111 '
#2240
0-
0,
0"
0:
1?
0C
b1110 !
b1110 +
1F
0J
12
09
00
07
0>
0E
0/
16
b0 $
b0 *
b1110 #
b1110 )
b1110 &
b0 '
#2250
08
1.
b1101 !
b1101 +
11
13
10
b1 $
b1 *
b1 '
#2260
1?
0.
0-
01
03
b1100 !
b1100 +
08
0<
00
17
b10 $
b10 *
b10 '
#2270
0?
1-
18
1<
1.
b1011 !
b1011 +
11
13
10
b11 $
b11 *
b11 '
#2280
1F
0.
0-
0,
01
03
18
0<
b1010 !
b1010 +
0?
0C
00
07
1>
b100 $
b100 *
b100 '
#2290
08
1.
b1001 !
b1001 +
11
13
10
b101 $
b101 *
b101 '
#2300
1F
0,
0?
0C
0.
0-
01
03
b1000 !
b1000 +
08
0<
00
17
b110 $
b110 *
b110 '
#2310
0F
1,
1?
1C
1-
18
1<
1.
b111 !
b111 +
11
13
10
b111 $
b111 *
b111 '
#2320
0.
0-
0,
0"
01
03
18
0<
1?
0C
b110 !
b110 +
0F
0J
00
07
0>
1E
b1000 $
b1000 *
b1000 '
#2330
08
1.
b101 !
b101 +
11
13
10
b1001 $
b1001 *
b1001 '
#2340
1?
0.
0-
01
03
b100 !
b100 +
08
0<
00
17
b1010 $
b1010 *
b1010 '
#2350
0?
1-
18
1<
1.
b11 !
b11 +
11
13
10
b1011 $
b1011 *
b1011 '
#2360
0"
0F
0J
0.
0-
0,
01
03
18
0<
b10 !
b10 +
0?
0C
00
07
1>
b1100 $
b1100 *
b1100 '
#2370
08
1.
b1 !
b1 +
11
13
10
b1101 $
b1101 *
b1101 '
#2380
0"
0F
0J
0,
0?
0C
0.
0-
01
03
b0 !
b0 +
08
0<
00
17
b1110 $
b1110 *
b1110 '
#2390
1"
1F
1J
1,
1?
1C
1-
18
1<
1.
b1111 !
b1111 +
11
13
10
b1111 $
b1111 *
b1111 '
