Multipliers/multiplier/half_adder.v
module half_adder(
input A, B,
output Sum, Carry);

xor(Sum,A,B);
and(Carry,A,B);

endmodule

Multipliers/multiplier/multiplier.v
module multiplier(
input [1:0] A,B,
output [3:0] P);

wire Z1,Z2,Z3,C;

and(P[0],A[0],B[0]);
and(Z1,A[1],B[0]);
and(Z2,A[0],B[1]);
and(Z3,A[1],B[1]);

half_adder HA1(
.A(Z1),
.B(Z2),
.Sum(P[1]),
.Carry(C));

half_adder HA2(
.A(C),
.B(Z3),
.Sum(P[2]),
.Carry(P[3]));

endmodule

Multipliers/multiplier/multiplier_tb.v
module multiplier_tb;

reg [1:0] A, B;
wire [3:0] P;

integer i, j;

multiplier dut(
    .A(A),
    .B(B),
    .P(P)
);

initial begin
    $dumpfile("multiplier.vcd");
    $dumpvars(0, multiplier_tb);

    for(i = 0; i < 4; i = i + 1) begin
        for(j = 0; j < 4; j = j + 1) begin
            A = i;
            B = j;
            #10;
        end
    end

    $finish;
end

initial begin
    $monitor("A=%b B=%b P=%b", A, B, P);
end

endmodule

Multipliers/multiplier/multiplier.vcd
$date
	Sat Jun 27 06:21:40 2026
$end
$version
	Icarus Verilog
$end
$timescale
	1s
$end
$scope module multiplier_tb $end
$var wire 4 ! P [3:0] $end
$var reg 2 " A [1:0] $end
$var reg 2 # B [1:0] $end
$var integer 32 $ i [31:0] $end
$var integer 32 % j [31:0] $end
$scope module dut $end
$var wire 2 & A [1:0] $end
$var wire 2 ' B [1:0] $end
$var wire 1 ( Z1 $end
$var wire 1 ) Z2 $end
$var wire 1 * Z3 $end
$var wire 4 + P [3:0] $end
$var wire 1 , C $end
$scope module HA1 $end
$var wire 1 ( A $end
$var wire 1 ) B $end
$var wire 1 , Carry $end
$var wire 1 - Sum $end
$upscope $end
$scope module HA2 $end
$var wire 1 , A $end
$var wire 1 * B $end
$var wire 1 . Carry $end
$var wire 1 / Sum $end
$upscope $end
$upscope $end
$upscope $end
$enddefinitions $end
$comment Show the parameter values. $end
$dumpall
$end
#0
$dumpvars
0/
0.
0-
0,
b0 +
0*
0)
0(
b0 '
b0 &
b0 %
b0 $
b0 #
b0 "
b0 !
$end
#10
b1 #
b1 '
b1 %
#20
b10 #
b10 '
b10 %
#30
b11 #
b11 '
b11 %
#40
b0 #
b0 '
b1 "
b1 &
b1 $
b0 %
#50
b1 !
b1 +
b1 #
b1 '
b1 %
#60
1-
b10 !
b10 +
1)
b10 #
b10 '
b10 %
#70
b11 !
b11 +
b11 #
b11 '
b11 %
#80
0-
b0 !
b0 +
0)
b0 #
b0 '
b10 "
b10 &
b10 $
b0 %
#90
b10 !
b10 +
1-
1(
b1 #
b1 '
b1 %
#100
0-
b100 !
b100 +
1/
0(
1*
b10 #
b10 '
b10 %
#110
b110 !
b110 +
1-
1(
b11 #
b11 '
b11 %
#120
0-
b0 !
b0 +
0/
0(
0*
b0 #
b0 '
b11 "
b11 &
b11 $
b0 %
#130
1-
b11 !
b11 +
1(
b1 #
b1 '
b1 %
#140
1/
b110 !
b110 +
0(
1)
1*
b10 #
b10 '
b10 %
#150
0/
1.
0-
1,
b1001 !
b1001 +
1(
b11 #
b11 '
b11 %
#160
b100 $
b100 %
