Adders/parallel_adder/detaflow_modeling/paraller_adder.v
module paraller_adder(
input [3:0]A,B,
input Cin,
output [3:0] S,
output Cout);

assign
{Cout,S}=A+B+Cin;

endmodule

Adders/parallel_adder/detaflow_modeling/paraller_adder_tb.v
module paraller_adder_tb;
reg [3:0]a,b;
reg cin;
wire [3:0] s;
wire cout;
integer i,j,k;

paraller_adder dut(
.A(a),
.B(b),
.Cin(cin),
.S(s),
.Cout(cout));

initial begin
$dumpfile("paraller_adder.vcd");
$dumpvars(0,paraller_adder_tb);

for(k=0; k<2; k=k+1) begin
cin= k;
for(i=0; i<16; i=i+1) begin
for(j=0; j<16; j=j+1)begin
a=i;
b=j;
#10;
end 
end
end
$finish;
end
endmodule

Adders/parallel_adder/detaflow_modeling/paraller_adder.vcd
$date
	Sat Jun 20 05:19:57 2026
$end
$version
	Icarus Verilog
$end
$timescale
	1s
$end
$scope module paraller_adder_tb $end
$var wire 4 ! s [3:0] $end
$var wire 1 " cout $end
$var reg 4 # a [3:0] $end
$var reg 4 $ b [3:0] $end
$var reg 1 % cin $end
$var integer 32 & i [31:0] $end
$var integer 32 ' j [31:0] $end
$var integer 32 ( k [31:0] $end
$scope module dut $end
$var wire 4 ) A [3:0] $end
$var wire 4 * B [3:0] $end
$var wire 1 % Cin $end
$var wire 4 + S [3:0] $end
$var wire 1 " Cout $end
$upscope $end
$upscope $end
$enddefinitions $end
$comment Show the parameter values. $end
$dumpall
$end
#0
$dumpvars
b0 +
b0 *
b0 )
b0 (
b0 '
b0 &
0%
b0 $
b0 #
0"
b0 !
$end
#10
b1 !
b1 +
b1 $
b1 *
b1 '
#20
b10 !
b10 +
b10 $
b10 *
b10 '
#30
b11 !
b11 +
b11 $
b11 *
b11 '
#40
b100 !
b100 +
b100 $
b100 *
b100 '
#50
b101 !
b101 +
b101 $
b101 *
b101 '
#60
b110 !
b110 +
b110 $
b110 *
b110 '
#70
b111 !
b111 +
b111 $
b111 *
b111 '
#80
b1000 !
b1000 +
b1000 $
b1000 *
b1000 '
#90
b1001 !
b1001 +
b1001 $
b1001 *
b1001 '
#100
b1010 !
b1010 +
b1010 $
b1010 *
b1010 '
#110
b1011 !
b1011 +
b1011 $
b1011 *
b1011 '
#120
b1100 !
b1100 +
b1100 $
b1100 *
b1100 '
#130
b1101 !
b1101 +
b1101 $
b1101 *
b1101 '
#140
b1110 !
b1110 +
b1110 $
b1110 *
b1110 '
#150
b1111 !
b1111 +
b1111 $
b1111 *
b1111 '
#160
b1 !
b1 +
b0 $
b0 *
b1 #
b1 )
b1 &
b0 '
#170
b10 !
b10 +
b1 $
b1 *
b1 '
#180
b11 !
b11 +
b10 $
b10 *
b10 '
#190
b100 !
b100 +
b11 $
b11 *
b11 '
#200
b101 !
b101 +
b100 $
b100 *
b100 '
#210
b110 !
b110 +
b101 $
b101 *
b101 '
#220
b111 !
b111 +
b110 $
b110 *
b110 '
#230
b1000 !
b1000 +
b111 $
b111 *
b111 '
#240
b1001 !
b1001 +
b1000 $
b1000 *
b1000 '
#250
b1010 !
b1010 +
b1001 $
b1001 *
b1001 '
#260
b1011 !
b1011 +
b1010 $
b1010 *
b1010 '
#270
b1100 !
b1100 +
b1011 $
b1011 *
b1011 '
#280
b1101 !
b1101 +
b1100 $
b1100 *
b1100 '
#290
b1110 !
b1110 +
b1101 $
b1101 *
b1101 '
#300
b1111 !
b1111 +
b1110 $
b1110 *
b1110 '
#310
b0 !
b0 +
1"
b1111 $
b1111 *
b1111 '
#320
0"
b10 !
b10 +
b0 $
b0 *
b10 #
b10 )
b10 &
b0 '
#330
b11 !
b11 +
b1 $
b1 *
b1 '
#340
b100 !
b100 +
b10 $
b10 *
b10 '
#350
b101 !
b101 +
b11 $
b11 *
b11 '
#360
b110 !
b110 +
b100 $
b100 *
b100 '
#370
b111 !
b111 +
b101 $
b101 *
b101 '
#380
b1000 !
b1000 +
b110 $
b110 *
b110 '
#390
b1001 !
b1001 +
b111 $
b111 *
b111 '
#400
b1010 !
b1010 +
b1000 $
b1000 *
b1000 '
#410
b1011 !
b1011 +
b1001 $
b1001 *
b1001 '
#420
b1100 !
b1100 +
b1010 $
b1010 *
b1010 '
#430
b1101 !
b1101 +
b1011 $
b1011 *
b1011 '
#440
b1110 !
b1110 +
b1100 $
b1100 *
b1100 '
#450
b1111 !
b1111 +
b1101 $
b1101 *
b1101 '
#460
b0 !
b0 +
1"
b1110 $
b1110 *
b1110 '
#470
b1 !
b1 +
b1111 $
b1111 *
b1111 '
#480
0"
b11 !
b11 +
b0 $
b0 *
b11 #
b11 )
b11 &
b0 '
#490
b100 !
b100 +
b1 $
b1 *
b1 '
#500
b101 !
b101 +
b10 $
b10 *
b10 '
#510
b110 !
b110 +
b11 $
b11 *
b11 '
#520
b111 !
b111 +
b100 $
b100 *
b100 '
#530
b1000 !
b1000 +
b101 $
b101 *
b101 '
#540
b1001 !
b1001 +
b110 $
b110 *
b110 '
#550
b1010 !
b1010 +
b111 $
b111 *
b111 '
#560
b1011 !
b1011 +
b1000 $
b1000 *
b1000 '
#570
b1100 !
b1100 +
b1001 $
b1001 *
b1001 '
#580
b1101 !
b1101 +
b1010 $
b1010 *
b1010 '
#590
b1110 !
b1110 +
b1011 $
b1011 *
b1011 '
#600
b1111 !
b1111 +
b1100 $
b1100 *
b1100 '
#610
b0 !
b0 +
1"
b1101 $
b1101 *
b1101 '
#620
b1 !
b1 +
b1110 $
b1110 *
b1110 '
#630
b10 !
b10 +
b1111 $
b1111 *
b1111 '
#640
0"
b100 !
b100 +
b0 $
b0 *
b100 #
b100 )
b100 &
b0 '
#650
b101 !
b101 +
b1 $
b1 *
b1 '
#660
b110 !
b110 +
b10 $
b10 *
b10 '
#670
b111 !
b111 +
b11 $
b11 *
b11 '
#680
b1000 !
b1000 +
b100 $
b100 *
b100 '
#690
b1001 !
b1001 +
b101 $
b101 *
b101 '
#700
b1010 !
b1010 +
b110 $
b110 *
b110 '
#710
b1011 !
b1011 +
b111 $
b111 *
b111 '
#720
b1100 !
b1100 +
b1000 $
b1000 *
b1000 '
#730
b1101 !
b1101 +
b1001 $
b1001 *
b1001 '
#740
b1110 !
b1110 +
b1010 $
b1010 *
b1010 '
#750
b1111 !
b1111 +
b1011 $
b1011 *
b1011 '
#760
b0 !
b0 +
1"
b1100 $
b1100 *
b1100 '
#770
b1 !
b1 +
b1101 $
b1101 *
b1101 '
#780
b10 !
b10 +
b1110 $
b1110 *
b1110 '
#790
b11 !
b11 +
b1111 $
b1111 *
b1111 '
#800
0"
b101 !
b101 +
b0 $
b0 *
b101 #
b101 )
b101 &
b0 '
#810
b110 !
b110 +
b1 $
b1 *
b1 '
#820
b111 !
b111 +
b10 $
b10 *
b10 '
#830
b1000 !
b1000 +
b11 $
b11 *
b11 '
#840
b1001 !
b1001 +
b100 $
b100 *
b100 '
#850
b1010 !
b1010 +
b101 $
b101 *
b101 '
#860
b1011 !
b1011 +
b110 $
b110 *
b110 '
#870
b1100 !
b1100 +
b111 $
b111 *
b111 '
#880
b1101 !
b1101 +
b1000 $
b1000 *
b1000 '
#890
b1110 !
b1110 +
b1001 $
b1001 *
b1001 '
#900
b1111 !
b1111 +
b1010 $
b1010 *
b1010 '
#910
b0 !
b0 +
1"
b1011 $
b1011 *
b1011 '
#920
b1 !
b1 +
b1100 $
b1100 *
b1100 '
#930
b10 !
b10 +
b1101 $
b1101 *
b1101 '
#940
b11 !
b11 +
b1110 $
b1110 *
b1110 '
#950
b100 !
b100 +
b1111 $
b1111 *
b1111 '
#960
0"
b110 !
b110 +
b0 $
b0 *
b110 #
b110 )
b110 &
b0 '
#970
b111 !
b111 +
b1 $
b1 *
b1 '
#980
b1000 !
b1000 +
b10 $
b10 *
b10 '
#990
b1001 !
b1001 +
b11 $
b11 *
b11 '
#1000
b1010 !
b1010 +
b100 $
b100 *
b100 '
#1010
b1011 !
b1011 +
b101 $
b101 *
b101 '
#1020
b1100 !
b1100 +
b110 $
b110 *
b110 '
#1030
b1101 !
b1101 +
b111 $
b111 *
b111 '
#1040
b1110 !
b1110 +
b1000 $
b1000 *
b1000 '
#1050
b1111 !
b1111 +
b1001 $
b1001 *
b1001 '
#1060
b0 !
b0 +
1"
b1010 $
b1010 *
b1010 '
#1070
b1 !
b1 +
b1011 $
b1011 *
b1011 '
#1080
b10 !
b10 +
b1100 $
b1100 *
b1100 '
#1090
b11 !
b11 +
b1101 $
b1101 *
b1101 '
#1100
b100 !
b100 +
b1110 $
b1110 *
b1110 '
#1110
b101 !
b101 +
b1111 $
b1111 *
b1111 '
#1120
0"
b111 !
b111 +
b0 $
b0 *
b111 #
b111 )
b111 &
b0 '
#1130
b1000 !
b1000 +
b1 $
b1 *
b1 '
#1140
b1001 !
b1001 +
b10 $
b10 *
b10 '
#1150
b1010 !
b1010 +
b11 $
b11 *
b11 '
#1160
b1011 !
b1011 +
b100 $
b100 *
b100 '
#1170
b1100 !
b1100 +
b101 $
b101 *
b101 '
#1180
b1101 !
b1101 +
b110 $
b110 *
b110 '
#1190
b1110 !
b1110 +
b111 $
b111 *
b111 '
#1200
b1111 !
b1111 +
b1000 $
b1000 *
b1000 '
#1210
b0 !
b0 +
1"
b1001 $
b1001 *
b1001 '
#1220
b1 !
b1 +
b1010 $
b1010 *
b1010 '
#1230
b10 !
b10 +
b1011 $
b1011 *
b1011 '
#1240
b11 !
b11 +
b1100 $
b1100 *
b1100 '
#1250
b100 !
b100 +
b1101 $
b1101 *
b1101 '
#1260
b101 !
b101 +
b1110 $
b1110 *
b1110 '
#1270
b110 !
b110 +
b1111 $
b1111 *
b1111 '
#1280
0"
b1000 !
b1000 +
b0 $
b0 *
b1000 #
b1000 )
b1000 &
b0 '
#1290
b1001 !
b1001 +
b1 $
b1 *
b1 '
#1300
b1010 !
b1010 +
b10 $
b10 *
b10 '
#1310
b1011 !
b1011 +
b11 $
b11 *
b11 '
#1320
b1100 !
b1100 +
b100 $
b100 *
b100 '
#1330
b1101 !
b1101 +
b101 $
b101 *
b101 '
#1340
b1110 !
b1110 +
b110 $
b110 *
b110 '
#1350
b1111 !
b1111 +
b111 $
b111 *
b111 '
#1360
b0 !
b0 +
1"
b1000 $
b1000 *
b1000 '
#1370
b1 !
b1 +
b1001 $
b1001 *
b1001 '
#1380
b10 !
b10 +
b1010 $
b1010 *
b1010 '
#1390
b11 !
b11 +
b1011 $
b1011 *
b1011 '
#1400
b100 !
b100 +
b1100 $
b1100 *
b1100 '
#1410
b101 !
b101 +
b1101 $
b1101 *
b1101 '
#1420
b110 !
b110 +
b1110 $
b1110 *
b1110 '
#1430
b111 !
b111 +
b1111 $
b1111 *
b1111 '
#1440
0"
b1001 !
b1001 +
b0 $
b0 *
b1001 #
b1001 )
b1001 &
b0 '
#1450
b1010 !
b1010 +
b1 $
b1 *
b1 '
#1460
b1011 !
b1011 +
b10 $
b10 *
b10 '
#1470
b1100 !
b1100 +
b11 $
b11 *
b11 '
#1480
b1101 !
b1101 +
b100 $
b100 *
b100 '
#1490
b1110 !
b1110 +
b101 $
b101 *
b101 '
#1500
b1111 !
b1111 +
b110 $
b110 *
b110 '
#1510
b0 !
b0 +
1"
b111 $
b111 *
b111 '
#1520
b1 !
b1 +
b1000 $
b1000 *
b1000 '
#1530
b10 !
b10 +
b1001 $
b1001 *
b1001 '
#1540
b11 !
b11 +
b1010 $
b1010 *
b1010 '
#1550
b100 !
b100 +
b1011 $
b1011 *
b1011 '
#1560
b101 !
b101 +
b1100 $
b1100 *
b1100 '
#1570
b110 !
b110 +
b1101 $
b1101 *
b1101 '
#1580
b111 !
b111 +
b1110 $
b1110 *
b1110 '
#1590
b1000 !
b1000 +
b1111 $
b1111 *
b1111 '
#1600
0"
b1010 !
b1010 +
b0 $
b0 *
b1010 #
b1010 )
b1010 &
b0 '
#1610
b1011 !
b1011 +
b1 $
b1 *
b1 '
#1620
b1100 !
b1100 +
b10 $
b10 *
b10 '
#1630
b1101 !
b1101 +
b11 $
b11 *
b11 '
#1640
b1110 !
b1110 +
b100 $
b100 *
b100 '
#1650
b1111 !
b1111 +
b101 $
b101 *
b101 '
#1660
b0 !
b0 +
1"
b110 $
b110 *
b110 '
#1670
b1 !
b1 +
b111 $
b111 *
b111 '
#1680
b10 !
b10 +
b1000 $
b1000 *
b1000 '
#1690
b11 !
b11 +
b1001 $
b1001 *
b1001 '
#1700
b100 !
b100 +
b1010 $
b1010 *
b1010 '
#1710
b101 !
b101 +
b1011 $
b1011 *
b1011 '
#1720
b110 !
b110 +
b1100 $
b1100 *
b1100 '
#1730
b111 !
b111 +
b1101 $
b1101 *
b1101 '
#1740
b1000 !
b1000 +
b1110 $
b1110 *
b1110 '
#1750
b1001 !
b1001 +
b1111 $
b1111 *
b1111 '
#1760
0"
b1011 !
b1011 +
b0 $
b0 *
b1011 #
b1011 )
b1011 &
b0 '
#1770
b1100 !
b1100 +
b1 $
b1 *
b1 '
#1780
b1101 !
b1101 +
b10 $
b10 *
b10 '
#1790
b1110 !
b1110 +
b11 $
b11 *
b11 '
#1800
b1111 !
b1111 +
b100 $
b100 *
b100 '
#1810
b0 !
b0 +
1"
b101 $
b101 *
b101 '
#1820
b1 !
b1 +
b110 $
b110 *
b110 '
#1830
b10 !
b10 +
b111 $
b111 *
b111 '
#1840
b11 !
b11 +
b1000 $
b1000 *
b1000 '
#1850
b100 !
b100 +
b1001 $
b1001 *
b1001 '
#1860
b101 !
b101 +
b1010 $
b1010 *
b1010 '
#1870
b110 !
b110 +
b1011 $
b1011 *
b1011 '
#1880
b111 !
b111 +
b1100 $
b1100 *
b1100 '
#1890
b1000 !
b1000 +
b1101 $
b1101 *
b1101 '
#1900
b1001 !
b1001 +
b1110 $
b1110 *
b1110 '
#1910
b1010 !
b1010 +
b1111 $
b1111 *
b1111 '
#1920
0"
b1100 !
b1100 +
b0 $
b0 *
b1100 #
b1100 )
b1100 &
b0 '
#1930
b1101 !
b1101 +
b1 $
b1 *
b1 '
#1940
b1110 !
b1110 +
b10 $
b10 *
b10 '
#1950
b1111 !
b1111 +
b11 $
b11 *
b11 '
#1960
b0 !
b0 +
1"
b100 $
b100 *
b100 '
#1970
b1 !
b1 +
b101 $
b101 *
b101 '
#1980
b10 !
b10 +
b110 $
b110 *
b110 '
#1990
b11 !
b11 +
b111 $
b111 *
b111 '
#2000
b100 !
b100 +
b1000 $
b1000 *
b1000 '
#2010
b101 !
b101 +
b1001 $
b1001 *
b1001 '
#2020
b110 !
b110 +
b1010 $
b1010 *
b1010 '
#2030
b111 !
b111 +
b1011 $
b1011 *
b1011 '
#2040
b1000 !
b1000 +
b1100 $
b1100 *
b1100 '
#2050
b1001 !
b1001 +
b1101 $
b1101 *
b1101 '
#2060
b1010 !
b1010 +
b1110 $
b1110 *
b1110 '
#2070
b1011 !
b1011 +
b1111 $
b1111 *
b1111 '
#2080
0"
b1101 !
b1101 +
b0 $
b0 *
b1101 #
b1101 )
b1101 &
b0 '
#2090
b1110 !
b1110 +
b1 $
b1 *
b1 '
#2100
b1111 !
b1111 +
b10 $
b10 *
b10 '
#2110
b0 !
b0 +
1"
b11 $
b11 *
b11 '
#2120
b1 !
b1 +
b100 $
b100 *
b100 '
#2130
b10 !
b10 +
b101 $
b101 *
b101 '
#2140
b11 !
b11 +
b110 $
b110 *
b110 '
#2150
b100 !
b100 +
b111 $
b111 *
b111 '
#2160
b101 !
b101 +
b1000 $
b1000 *
b1000 '
#2170
b110 !
b110 +
b1001 $
b1001 *
b1001 '
#2180
b111 !
b111 +
b1010 $
b1010 *
b1010 '
#2190
b1000 !
b1000 +
b1011 $
b1011 *
b1011 '
#2200
b1001 !
b1001 +
b1100 $
b1100 *
b1100 '
#2210
b1010 !
b1010 +
b1101 $
b1101 *
b1101 '
#2220
b1011 !
b1011 +
b1110 $
b1110 *
b1110 '
#2230
b1100 !
b1100 +
b1111 $
b1111 *
b1111 '
#2240
0"
b1110 !
b1110 +
b0 $
b0 *
b1110 #
b1110 )
b1110 &
b0 '
#2250
b1111 !
b1111 +
b1 $
b1 *
b1 '
#2260
b0 !
b0 +
1"
b10 $
b10 *
b10 '
#2270
b1 !
b1 +
b11 $
b11 *
b11 '
#2280
b10 !
b10 +
b100 $
b100 *
b100 '
#2290
b11 !
b11 +
b101 $
b101 *
b101 '
#2300
b100 !
b100 +
b110 $
b110 *
b110 '
#2310
b101 !
b101 +
b111 $
b111 *
b111 '
#2320
b110 !
b110 +
b1000 $
b1000 *
b1000 '
#2330
b111 !
b111 +
b1001 $
b1001 *
b1001 '
#2340
b1000 !
b1000 +
b1010 $
b1010 *
b1010 '
#2350
b1001 !
b1001 +
b1011 $
b1011 *
b1011 '
#2360
b1010 !
b1010 +
b1100 $
b1100 *
b1100 '
#2370
b1011 !
b1011 +
b1101 $
b1101 *
b1101 '
#2380
b1100 !
b1100 +
b1110 $
b1110 *
b1110 '
#2390
b1101 !
b1101 +
b1111 $
b1111 *
b1111 '
#2400
0"
b1111 !
b1111 +
b0 $
b0 *
b1111 #
b1111 )
b1111 &
b0 '
#2410
b0 !
b0 +
1"
b1 $
b1 *
b1 '
#2420
b1 !
b1 +
b10 $
b10 *
b10 '
#2430
b10 !
b10 +
b11 $
b11 *
b11 '
#2440
b11 !
b11 +
b100 $
b100 *
b100 '
#2450
b100 !
b100 +
b101 $
b101 *
b101 '
#2460
b101 !
b101 +
b110 $
b110 *
b110 '
#2470
b110 !
b110 +
b111 $
b111 *
b111 '
#2480
b111 !
b111 +
b1000 $
b1000 *
b1000 '
#2490
b1000 !
b1000 +
b1001 $
b1001 *
b1001 '
#2500
b1001 !
b1001 +
b1010 $
b1010 *
b1010 '
#2510
b1010 !
b1010 +
b1011 $
b1011 *
b1011 '
#2520
b1011 !
b1011 +
b1100 $
b1100 *
b1100 '
#2530
b1100 !
b1100 +
b1101 $
b1101 *
b1101 '
#2540
b1101 !
b1101 +
b1110 $
b1110 *
b1110 '
#2550
b1110 !
b1110 +
b1111 $
b1111 *
b1111 '
#2560
0"
b1 !
b1 +
b0 $
b0 *
b0 #
b0 )
1%
b1 (
b0 &
b0 '
#2570
b10 !
b10 +
b1 $
b1 *
b1 '
#2580
b11 !
b11 +
b10 $
b10 *
b10 '
#2590
b100 !
b100 +
b11 $
b11 *
b11 '
#2600
b101 !
b101 +
b100 $
b100 *
b100 '
#2610
b110 !
b110 +
b101 $
b101 *
b101 '
#2620
b111 !
b111 +
b110 $
b110 *
b110 '
#2630
b1000 !
b1000 +
b111 $
b111 *
b111 '
#2640
b1001 !
b1001 +
b1000 $
b1000 *
b1000 '
#2650
b1010 !
b1010 +
b1001 $
b1001 *
b1001 '
#2660
b1011 !
b1011 +
b1010 $
b1010 *
b1010 '
#2670
b1100 !
b1100 +
b1011 $
b1011 *
b1011 '
#2680
b1101 !
b1101 +
b1100 $
b1100 *
b1100 '
#2690
b1110 !
b1110 +
b1101 $
b1101 *
b1101 '
#2700
b1111 !
b1111 +
b1110 $
b1110 *
b1110 '
#2710
b0 !
b0 +
1"
b1111 $
b1111 *
b1111 '
#2720
0"
b10 !
b10 +
b0 $
b0 *
b1 #
b1 )
b1 &
b0 '
#2730
b11 !
b11 +
b1 $
b1 *
b1 '
#2740
b100 !
b100 +
b10 $
b10 *
b10 '
#2750
b101 !
b101 +
b11 $
b11 *
b11 '
#2760
b110 !
b110 +
b100 $
b100 *
b100 '
#2770
b111 !
b111 +
b101 $
b101 *
b101 '
#2780
b1000 !
b1000 +
b110 $
b110 *
b110 '
#2790
b1001 !
b1001 +
b111 $
b111 *
b111 '
#2800
b1010 !
b1010 +
b1000 $
b1000 *
b1000 '
#2810
b1011 !
b1011 +
b1001 $
b1001 *
b1001 '
#2820
b1100 !
b1100 +
b1010 $
b1010 *
b1010 '
#2830
b1101 !
b1101 +
b1011 $
b1011 *
b1011 '
#2840
b1110 !
b1110 +
b1100 $
b1100 *
b1100 '
#2850
b1111 !
b1111 +
b1101 $
b1101 *
b1101 '
#2860
b0 !
b0 +
1"
b1110 $
b1110 *
b1110 '
#2870
b1 !
b1 +
b1111 $
b1111 *
b1111 '
#2880
0"
b11 !
b11 +
b0 $
b0 *
b10 #
b10 )
b10 &
b0 '
#2890
b100 !
b100 +
b1 $
b1 *
b1 '
#2900
b101 !
b101 +
b10 $
b10 *
b10 '
#2910
b110 !
b110 +
b11 $
b11 *
b11 '
#2920
b111 !
b111 +
b100 $
b100 *
b100 '
#2930
b1000 !
b1000 +
b101 $
b101 *
b101 '
#2940
b1001 !
b1001 +
b110 $
b110 *
b110 '
#2950
b1010 !
b1010 +
b111 $
b111 *
b111 '
#2960
b1011 !
b1011 +
b1000 $
b1000 *
b1000 '
#2970
b1100 !
b1100 +
b1001 $
b1001 *
b1001 '
#2980
b1101 !
b1101 +
b1010 $
b1010 *
b1010 '
#2990
b1110 !
b1110 +
b1011 $
b1011 *
b1011 '
#3000
b1111 !
b1111 +
b1100 $
b1100 *
b1100 '
#3010
b0 !
b0 +
1"
b1101 $
b1101 *
b1101 '
#3020
b1 !
b1 +
b1110 $
b1110 *
b1110 '
#3030
b10 !
b10 +
b1111 $
b1111 *
b1111 '
#3040
0"
b100 !
b100 +
b0 $
b0 *
b11 #
b11 )
b11 &
b0 '
#3050
b101 !
b101 +
b1 $
b1 *
b1 '
#3060
b110 !
b110 +
b10 $
b10 *
b10 '
#3070
b111 !
b111 +
b11 $
b11 *
b11 '
#3080
b1000 !
b1000 +
b100 $
b100 *
b100 '
#3090
b1001 !
b1001 +
b101 $
b101 *
b101 '
#3100
b1010 !
b1010 +
b110 $
b110 *
b110 '
#3110
b1011 !
b1011 +
b111 $
b111 *
b111 '
#3120
b1100 !
b1100 +
b1000 $
b1000 *
b1000 '
#3130
b1101 !
b1101 +
b1001 $
b1001 *
b1001 '
#3140
b1110 !
b1110 +
b1010 $
b1010 *
b1010 '
#3150
b1111 !
b1111 +
b1011 $
b1011 *
b1011 '
#3160
b0 !
b0 +
1"
b1100 $
b1100 *
b1100 '
#3170
b1 !
b1 +
b1101 $
b1101 *
b1101 '
#3180
b10 !
b10 +
b1110 $
b1110 *
b1110 '
#3190
b11 !
b11 +
b1111 $
b1111 *
b1111 '
#3200
0"
b101 !
b101 +
b0 $
b0 *
b100 #
b100 )
b100 &
b0 '
#3210
b110 !
b110 +
b1 $
b1 *
b1 '
#3220
b111 !
b111 +
b10 $
b10 *
b10 '
#3230
b1000 !
b1000 +
b11 $
b11 *
b11 '
#3240
b1001 !
b1001 +
b100 $
b100 *
b100 '
#3250
b1010 !
b1010 +
b101 $
b101 *
b101 '
#3260
b1011 !
b1011 +
b110 $
b110 *
b110 '
#3270
b1100 !
b1100 +
b111 $
b111 *
b111 '
#3280
b1101 !
b1101 +
b1000 $
b1000 *
b1000 '
#3290
b1110 !
b1110 +
b1001 $
b1001 *
b1001 '
#3300
b1111 !
b1111 +
b1010 $
b1010 *
b1010 '
#3310
b0 !
b0 +
1"
b1011 $
b1011 *
b1011 '
#3320
b1 !
b1 +
b1100 $
b1100 *
b1100 '
#3330
b10 !
b10 +
b1101 $
b1101 *
b1101 '
#3340
b11 !
b11 +
b1110 $
b1110 *
b1110 '
#3350
b100 !
b100 +
b1111 $
b1111 *
b1111 '
#3360
0"
b110 !
b110 +
b0 $
b0 *
b101 #
b101 )
b101 &
b0 '
#3370
b111 !
b111 +
b1 $
b1 *
b1 '
#3380
b1000 !
b1000 +
b10 $
b10 *
b10 '
#3390
b1001 !
b1001 +
b11 $
b11 *
b11 '
#3400
b1010 !
b1010 +
b100 $
b100 *
b100 '
#3410
b1011 !
b1011 +
b101 $
b101 *
b101 '
#3420
b1100 !
b1100 +
b110 $
b110 *
b110 '
#3430
b1101 !
b1101 +
b111 $
b111 *
b111 '
#3440
b1110 !
b1110 +
b1000 $
b1000 *
b1000 '
#3450
b1111 !
b1111 +
b1001 $
b1001 *
b1001 '
#3460
b0 !
b0 +
1"
b1010 $
b1010 *
b1010 '
#3470
b1 !
b1 +
b1011 $
b1011 *
b1011 '
#3480
b10 !
b10 +
b1100 $
b1100 *
b1100 '
#3490
b11 !
b11 +
b1101 $
b1101 *
b1101 '
#3500
b100 !
b100 +
b1110 $
b1110 *
b1110 '
#3510
b101 !
b101 +
b1111 $
b1111 *
b1111 '
#3520
0"
b111 !
b111 +
b0 $
b0 *
b110 #
b110 )
b110 &
b0 '
#3530
b1000 !
b1000 +
b1 $
b1 *
b1 '
#3540
b1001 !
b1001 +
b10 $
b10 *
b10 '
#3550
b1010 !
b1010 +
b11 $
b11 *
b11 '
#3560
b1011 !
b1011 +
b100 $
b100 *
b100 '
#3570
b1100 !
b1100 +
b101 $
b101 *
b101 '
#3580
b1101 !
b1101 +
b110 $
b110 *
b110 '
#3590
b1110 !
b1110 +
b111 $
b111 *
b111 '
#3600
b1111 !
b1111 +
b1000 $
b1000 *
b1000 '
#3610
b0 !
b0 +
1"
b1001 $
b1001 *
b1001 '
#3620
b1 !
b1 +
b1010 $
b1010 *
b1010 '
#3630
b10 !
b10 +
b1011 $
b1011 *
b1011 '
#3640
b11 !
b11 +
b1100 $
b1100 *
b1100 '
#3650
b100 !
b100 +
b1101 $
b1101 *
b1101 '
#3660
b101 !
b101 +
b1110 $
b1110 *
b1110 '
#3670
b110 !
b110 +
b1111 $
b1111 *
b1111 '
#3680
0"
b1000 !
b1000 +
b0 $
b0 *
b111 #
b111 )
b111 &
b0 '
#3690
b1001 !
b1001 +
b1 $
b1 *
b1 '
#3700
b1010 !
b1010 +
b10 $
b10 *
b10 '
#3710
b1011 !
b1011 +
b11 $
b11 *
b11 '
#3720
b1100 !
b1100 +
b100 $
b100 *
b100 '
#3730
b1101 !
b1101 +
b101 $
b101 *
b101 '
#3740
b1110 !
b1110 +
b110 $
b110 *
b110 '
#3750
b1111 !
b1111 +
b111 $
b111 *
b111 '
#3760
b0 !
b0 +
1"
b1000 $
b1000 *
b1000 '
#3770
b1 !
b1 +
b1001 $
b1001 *
b1001 '
#3780
b10 !
b10 +
b1010 $
b1010 *
b1010 '
#3790
b11 !
b11 +
b1011 $
b1011 *
b1011 '
#3800
b100 !
b100 +
b1100 $
b1100 *
b1100 '
#3810
b101 !
b101 +
b1101 $
b1101 *
b1101 '
#3820
b110 !
b110 +
b1110 $
b1110 *
b1110 '
#3830
b111 !
b111 +
b1111 $
b1111 *
b1111 '
#3840
0"
b1001 !
b1001 +
b0 $
b0 *
b1000 #
b1000 )
b1000 &
b0 '
#3850
b1010 !
b1010 +
b1 $
b1 *
b1 '
#3860
b1011 !
b1011 +
b10 $
b10 *
b10 '
#3870
b1100 !
b1100 +
b11 $
b11 *
b11 '
#3880
b1101 !
b1101 +
b100 $
b100 *
b100 '
#3890
b1110 !
b1110 +
b101 $
b101 *
b101 '
#3900
b1111 !
b1111 +
b110 $
b110 *
b110 '
#3910
b0 !
b0 +
1"
b111 $
b111 *
b111 '
#3920
b1 !
b1 +
b1000 $
b1000 *
b1000 '
#3930
b10 !
b10 +
b1001 $
b1001 *
b1001 '
#3940
b11 !
b11 +
b1010 $
b1010 *
b1010 '
#3950
b100 !
b100 +
b1011 $
b1011 *
b1011 '
#3960
b101 !
b101 +
b1100 $
b1100 *
b1100 '
#3970
b110 !
b110 +
b1101 $
b1101 *
b1101 '
#3980
b111 !
b111 +
b1110 $
b1110 *
b1110 '
#3990
b1000 !
b1000 +
b1111 $
b1111 *
b1111 '
#4000
0"
b1010 !
b1010 +
b0 $
b0 *
b1001 #
b1001 )
b1001 &
b0 '
#4010
b1011 !
b1011 +
b1 $
b1 *
b1 '
#4020
b1100 !
b1100 +
b10 $
b10 *
b10 '
#4030
b1101 !
b1101 +
b11 $
b11 *
b11 '
#4040
b1110 !
b1110 +
b100 $
b100 *
b100 '
#4050
b1111 !
b1111 +
b101 $
b101 *
b101 '
#4060
b0 !
b0 +
1"
b110 $
b110 *
b110 '
#4070
b1 !
b1 +
b111 $
b111 *
b111 '
#4080
b10 !
b10 +
b1000 $
b1000 *
b1000 '
#4090
b11 !
b11 +
b1001 $
b1001 *
b1001 '
#4100
b100 !
b100 +
b1010 $
b1010 *
b1010 '
#4110
b101 !
b101 +
b1011 $
b1011 *
b1011 '
#4120
b110 !
b110 +
b1100 $
b1100 *
b1100 '
#4130
b111 !
b111 +
b1101 $
b1101 *
b1101 '
#4140
b1000 !
b1000 +
b1110 $
b1110 *
b1110 '
#4150
b1001 !
b1001 +
b1111 $
b1111 *
b1111 '
#4160
0"
b1011 !
b1011 +
b0 $
b0 *
b1010 #
b1010 )
b1010 &
b0 '
#4170
b1100 !
b1100 +
b1 $
b1 *
b1 '
#4180
b1101 !
b1101 +
b10 $
b10 *
b10 '
#4190
b1110 !
b1110 +
b11 $
b11 *
b11 '
#4200
b1111 !
b1111 +
b100 $
b100 *
b100 '
#4210
b0 !
b0 +
1"
b101 $
b101 *
b101 '
#4220
b1 !
b1 +
b110 $
b110 *
b110 '
#4230
b10 !
b10 +
b111 $
b111 *
b111 '
#4240
b11 !
b11 +
b1000 $
b1000 *
b1000 '
#4250
b100 !
b100 +
b1001 $
b1001 *
b1001 '
#4260
b101 !
b101 +
b1010 $
b1010 *
b1010 '
#4270
b110 !
b110 +
b1011 $
b1011 *
b1011 '
#4280
b111 !
b111 +
b1100 $
b1100 *
b1100 '
#4290
b1000 !
b1000 +
b1101 $
b1101 *
b1101 '
#4300
b1001 !
b1001 +
b1110 $
b1110 *
b1110 '
#4310
b1010 !
b1010 +
b1111 $
b1111 *
b1111 '
#4320
0"
b1100 !
b1100 +
b0 $
b0 *
b1011 #
b1011 )
b1011 &
b0 '
#4330
b1101 !
b1101 +
b1 $
b1 *
b1 '
#4340
b1110 !
b1110 +
b10 $
b10 *
b10 '
