Adders/adder_subtractor/full_adder.v
module full_adder(
input A, B, C,
output Sum, Carry);

wire a1,a2,a3;

xor(Sum,A,B,C);
and(a1,A,B);
and(a2,A,C);
and(a3,C,B);
or(Carry,a1,a2,a3);
endmodule

Adders/parallel_adder/structural_modeling/paraller_adder.v
module paraller_adder(
input [3:0] A,B,
input Cin,
output [3:0] S,
output Cout);

wire [2:0] C;

full_adder FA0(
.A(A[0]),
.B(B[0]),
.C(Cin),
.Sum(S[0]),
.Carry(C[0]));

full_adder FA1(
.A(A[1]),
.B(B[1]),
.C(C[0]),
.Sum(S[1]),
.Carry(C[1]));

full_adder FA2(
.A(A[2]),
.B(B[2]),
.C(C[1]),
.Sum(S[2]),
.Carry(C[2]));

full_adder FA3(
.A(A[3]),
.B(B[3]),
.C(C[2]),
.Sum(S[3]),
.Carry(Cout));

endmodule

Adders/parallel_adder/structural_modeling/paraller_adder_tb.v
module paraller_adder_tb;
reg [3:0]a,b;
reg cin;
wire [3:0]s;
wire cout;
integer i,j,k;
paraller_adder dut (
.A(a),
.B(b),
.Cin(cin),
.S(s),
.Cout(cout));

initial begin 
$dumpfile("paraller_adder.vcd");
$dumpvars(0,paraller_adder_tb);

for(k=0; k<2; k=k+1) begin
cin= k;

for(i=0; i<16; i=i+1)begin
for(j=0; j<16; j=j+1) begin
a=i;
b=j;
#10;
end
end
end
$finish;
end
endmodule

Adders/parallel_adder/structural_modeling/paraller_adder.vcd
$date
	Fri Jun 19 16:34:56 2026
$end
$version
	Icarus Verilog
$end
$timescale
	1s
$end
$scope module paraller_adder_tb $end
$var wire 4 ! s [3:0] $end
$var wire 1 " cout $end
$var reg 4 # a [3:0] $end
$var reg 4 $ b [3:0] $end
$var reg 1 % cin $end
$var integer 32 & i [31:0] $end
$var integer 32 ' j [31:0] $end
$var integer 32 ( k [31:0] $end
$scope module dut $end
$var wire 4 ) A [3:0] $end
$var wire 4 * B [3:0] $end
$var wire 1 % Cin $end
$var wire 4 + S [3:0] $end
$var wire 1 " Cout $end
$var wire 3 , C [2:0] $end
$scope module FA0 $end
$var wire 1 - A $end
$var wire 1 . B $end
$var wire 1 % C $end
$var wire 1 / Carry $end
$var wire 1 0 Sum $end
$var wire 1 1 a1 $end
$var wire 1 2 a2 $end
$var wire 1 3 a3 $end
$upscope $end
$scope module FA1 $end
$var wire 1 4 A $end
$var wire 1 5 B $end
$var wire 1 6 C $end
$var wire 1 7 Carry $end
$var wire 1 8 Sum $end
$var wire 1 9 a1 $end
$var wire 1 : a2 $end
$var wire 1 ; a3 $end
$upscope $end
$scope module FA2 $end
$var wire 1 < A $end
$var wire 1 = B $end
$var wire 1 > C $end
$var wire 1 ? Carry $end
$var wire 1 @ Sum $end
$var wire 1 A a1 $end
$var wire 1 B a2 $end
$var wire 1 C a3 $end
$upscope $end
$scope module FA3 $end
$var wire 1 D A $end
$var wire 1 E B $end
$var wire 1 F C $end
$var wire 1 " Carry $end
$var wire 1 G Sum $end
$var wire 1 H a1 $end
$var wire 1 I a2 $end
$var wire 1 J a3 $end
$upscope $end
$upscope $end
$upscope $end
$enddefinitions $end
$comment Show the parameter values. $end
$dumpall
$end
#0
$dumpvars
0J
0I
0H
0G
0F
0E
0D
0C
0B
0A
0@
0?
0>
0=
0<
0;
0:
09
08
07
06
05
04
03
02
01
00
0/
0.
0-
b0 ,
b0 +
b0 *
b0 )
b0 (
b0 '
b0 &
0%
b0 $
b0 #
0"
b0 !
$end
#10
b1 !
b1 +
10
1.
b1 $
b1 *
b1 '
#20
00
b10 !
b10 +
18
0.
15
b10 $
b10 *
b10 '
#30
b11 !
b11 +
10
1.
b11 $
b11 *
b11 '
#40
00
08
b100 !
b100 +
1@
0.
05
1=
b100 $
b100 *
b100 '
#50
b101 !
b101 +
10
1.
b101 $
b101 *
b101 '
#60
00
b110 !
b110 +
18
0.
15
b110 $
b110 *
b110 '
#70
b111 !
b111 +
10
1.
b111 $
b111 *
b111 '
#80
00
08
0@
b1000 !
b1000 +
1G
0.
05
0=
1E
b1000 $
b1000 *
b1000 '
#90
b1001 !
b1001 +
10
1.
b1001 $
b1001 *
b1001 '
#100
00
b1010 !
b1010 +
18
0.
15
b1010 $
b1010 *
b1010 '
#110
b1011 !
b1011 +
10
1.
b1011 $
b1011 *
b1011 '
#120
00
08
b1100 !
b1100 +
1@
0.
05
1=
b1100 $
b1100 *
b1100 '
#130
b1101 !
b1101 +
10
1.
b1101 $
b1101 *
b1101 '
#140
00
b1110 !
b1110 +
18
0.
15
b1110 $
b1110 *
b1110 '
#150
b1111 !
b1111 +
10
1.
b1111 $
b1111 *
b1111 '
#160
08
0@
b1 !
b1 +
0G
0.
05
0=
0E
1-
b0 $
b0 *
b1 #
b1 )
b1 &
b0 '
#170
18
16
b1 ,
1/
b10 !
b10 +
00
11
1.
b1 $
b1 *
b1 '
#180
0@
06
0>
0/
b0 ,
07
10
01
b11 !
b11 +
18
0;
0.
15
b10 $
b10 *
b10 '
#190
1@
1>
17
08
1;
16
b11 ,
1/
b100 !
b100 +
00
11
1.
b11 $
b11 *
b11 '
#200
0G
06
0>
0F
0/
07
b0 ,
0?
10
01
08
0;
b101 !
b101 +
1@
0C
0.
05
1=
b100 $
b100 *
b100 '
#210
18
16
b1 ,
1/
b110 !
b110 +
00
11
1.
b101 $
b101 *
b101 '
#220
0G
0F
0?
1@
0C
06
0>
0/
b0 ,
07
10
01
b111 !
b111 +
18
0;
0.
15
b110 $
b110 *
b110 '
#230
1G
1F
1?
0@
1C
1>
17
08
1;
16
b111 ,
1/
b1000 !
b1000 +
00
11
1.
b111 $
b111 *
b111 '
#240
06
0>
0F
0/
07
b0 ,
0?
0"
10
01
08
0;
0@
0C
b1001 !
b1001 +
1G
0J
0.
05
0=
1E
b1000 $
b1000 *
b1000 '
#250
18
16
b1 ,
1/
b1010 !
b1010 +
00
11
1.
b1001 $
b1001 *
b1001 '
#260
0@
06
0>
0/
b0 ,
07
10
01
b1011 !
b1011 +
18
0;
0.
15
b1010 $
b1010 *
b1010 '
#270
1@
1>
17
08
1;
16
b11 ,
1/
b1100 !
b1100 +
00
11
1.
b1011 $
b1011 *
b1011 '
#280
0"
1G
0J
06
0>
0F
0/
07
b0 ,
0?
10
01
08
0;
b1101 !
b1101 +
1@
0C
0.
05
1=
b1100 $
b1100 *
b1100 '
#290
18
16
b1 ,
1/
b1110 !
b1110 +
00
11
1.
b1101 $
b1101 *
b1101 '
#300
0"
1G
0J
0F
0?
1@
0C
06
0>
0/
b0 ,
07
10
01
b1111 !
b1111 +
18
0;
0.
15
b1110 $
b1110 *
b1110 '
#310
1"
0G
1J
1F
1?
0@
1C
1>
17
08
1;
16
b111 ,
1/
b0 !
b0 +
00
11
1.
b1111 $
b1111 *
b1111 '
#320
0>
07
18
0F
06
0?
0"
b0 ,
0/
0;
0@
0C
b10 !
b10 +
0G
0J
01
0:
0.
05
0=
0E
0-
14
b0 $
b0 *
b10 #
b10 )
b10 &
b0 '
#330
b11 !
b11 +
10
1.
b1 $
b1 *
b1 '
#340
1@
1>
b10 ,
17
00
b100 !
b100 +
08
19
0.
15
b10 $
b10 *
b10 '
#350
b101 !
b101 +
10
1.
b11 $
b11 *
b11 '
#360
0G
0>
0F
07
b0 ,
0?
00
18
09
b110 !
b110 +
1@
0C
0.
05
1=
b100 $
b100 *
b100 '
#370
b111 !
b111 +
10
1.
b101 $
b101 *
b101 '
#380
1G
1F
1?
0@
1C
1>
b110 ,
17
00
b1000 !
b1000 +
08
19
0.
15
b110 $
b110 *
b110 '
#390
b1001 !
b1001 +
10
1.
b111 $
b111 *
b111 '
#400
0>
0F
07
b0 ,
0?
0"
00
18
09
0@
0C
b1010 !
b1010 +
1G
0J
0.
05
0=
1E
b1000 $
b1000 *
b1000 '
#410
b1011 !
b1011 +
10
1.
b1001 $
b1001 *
b1001 '
#420
1@
1>
b10 ,
17
00
b1100 !
b1100 +
08
19
0.
15
b1010 $
b1010 *
b1010 '
#430
b1101 !
b1101 +
10
1.
b1011 $
b1011 *
b1011 '
#440
0"
1G
0J
0>
0F
07
b0 ,
0?
00
18
09
b1110 !
b1110 +
1@
0C
0.
05
1=
b1100 $
b1100 *
b1100 '
#450
b1111 !
b1111 +
10
1.
b1101 $
b1101 *
b1101 '
#460
1"
0G
1J
1F
1?
0@
1C
1>
b110 ,
17
00
b0 !
b0 +
08
19
0.
15
b1110 $
b1110 *
b1110 '
#470
b1 !
b1 +
10
1.
b1111 $
b1111 *
b1111 '
#480
0>
0F
07
b0 ,
0?
0"
18
09
0@
0C
b11 !
b11 +
0G
0J
0.
05
0=
0E
1-
b0 $
b0 *
b11 #
b11 )
b11 &
b0 '
#490
1@
1>
17
08
1:
16
b11 ,
1/
b100 !
b100 +
00
11
1.
b1 $
b1 *
b1 '
#500
0:
06
b10 ,
0/
10
01
b101 !
b101 +
08
19
0;
0.
15
b10 $
b10 *
b10 '
#510
18
1:
1;
16
b11 ,
1/
b110 !
b110 +
00
11
1.
b11 $
b11 *
b11 '
#520
0>
07
0:
0G
06
0F
0/
b0 ,
0?
10
01
18
09
0;
b111 !
b111 +
1@
0C
0.
05
1=
b100 $
b100 *
b100 '
#530
1G
1F
1?
0@
1C
1>
17
08
1:
16
b111 ,
1/
b1000 !
b1000 +
00
11
1.
b101 $
b101 *
b101 '
#540
0:
06
b110 ,
0/
10
01
b1001 !
b1001 +
08
19
0;
0.
15
b110 $
b110 *
b110 '
#550
18
1:
1;
16
b111 ,
1/
b1010 !
b1010 +
00
11
1.
b111 $
b111 *
b111 '
#560
0>
07
0:
06
0F
0/
b0 ,
0?
0"
10
01
18
09
0;
0@
0C
b1011 !
b1011 +
1G
0J
0.
05
0=
1E
b1000 $
b1000 *
b1000 '
#570
1@
1>
17
08
1:
16
b11 ,
1/
b1100 !
b1100 +
00
11
1.
b1001 $
b1001 *
b1001 '
#580
0:
06
b10 ,
0/
10
01
b1101 !
b1101 +
08
19
0;
0.
15
b1010 $
b1010 *
b1010 '
#590
18
1:
1;
16
b11 ,
1/
b1110 !
b1110 +
00
11
1.
b1011 $
b1011 *
b1011 '
#600
0>
07
0"
0:
1G
0J
06
0F
0/
b0 ,
0?
10
01
18
09
0;
b1111 !
b1111 +
1@
0C
0.
05
1=
b1100 $
b1100 *
b1100 '
#610
1"
0G
1J
1F
1?
0@
1C
1>
17
08
1:
16
b111 ,
1/
b0 !
b0 +
00
11
1.
b1101 $
b1101 *
b1101 '
#620
0:
06
b110 ,
0/
10
01
b1 !
b1 +
08
19
0;
0.
15
b1110 $
b1110 *
b1110 '
#630
18
1:
1;
16
b111 ,
1/
b10 !
b10 +
00
11
1.
b1111 $
b1111 *
b1111 '
#640
0F
0?
08
1@
06
0>
0"
0/
b0 ,
07
0;
0C
b100 !
b100 +
0G
0J
01
09
0:
0B
0.
05
0=
0E
0-
04
1<
b0 $
b0 *
b100 #
b100 )
b100 &
b0 '
#650
b101 !
b101 +
10
1.
b1 $
b1 *
b1 '
#660
00
b110 !
b110 +
18
0.
15
b10 $
b10 *
b10 '
#670
b111 !
b111 +
10
1.
b11 $
b11 *
b11 '
#680
1G
1F
b100 ,
1?
00
08
b1000 !
b1000 +
0@
1A
0.
05
1=
b100 $
b100 *
b100 '
#690
b1001 !
b1001 +
10
1.
b101 $
b101 *
b101 '
#700
00
b1010 !
b1010 +
18
0.
15
b110 $
b110 *
b110 '
#710
b1011 !
b1011 +
10
1.
b111 $
b111 *
b111 '
#720
0F
b0 ,
0?
0"
00
08
1@
0A
b1100 !
b1100 +
1G
0J
0.
05
0=
1E
b1000 $
b1000 *
b1000 '
#730
b1101 !
b1101 +
10
1.
b1001 $
b1001 *
b1001 '
#740
00
b1110 !
b1110 +
18
0.
15
b1010 $
b1010 *
b1010 '
#750
b1111 !
b1111 +
10
1.
b1011 $
b1011 *
b1011 '
#760
1"
0G
1J
1F
b100 ,
1?
00
08
b0 !
b0 +
0@
1A
0.
05
1=
b1100 $
b1100 *
b1100 '
#770
b1 !
b1 +
10
1.
b1101 $
b1101 *
b1101 '
#780
00
b10 !
b10 +
18
0.
15
b1110 $
b1110 *
b1110 '
#790
b11 !
b11 +
10
1.
b1111 $
b1111 *
b1111 '
#800
0F
b0 ,
0?
0"
08
1@
0A
b101 !
b101 +
0G
0J
0.
05
0=
0E
1-
b0 $
b0 *
b101 #
b101 )
b101 &
b0 '
#810
18
16
b1 ,
1/
b110 !
b110 +
00
11
1.
b1 $
b1 *
b1 '
#820
0G
0F
0?
1@
0B
06
0>
0/
b0 ,
07
10
01
b111 !
b111 +
18
0;
0.
15
b10 $
b10 *
b10 '
#830
1G
1F
1?
0@
1B
1>
17
08
1;
16
b111 ,
1/
b1000 !
b1000 +
00
11
1.
b11 $
b11 *
b11 '
#840
0B
06
0>
0/
b100 ,
07
10
01
08
0;
b1001 !
b1001 +
0@
1A
0C
0.
05
1=
b100 $
b100 *
b100 '
#850
18
16
b101 ,
1/
b1010 !
b1010 +
00
11
1.
b101 $
b101 *
b101 '
#860
0@
0B
0C
06
0>
0/
b100 ,
07
10
01
b1011 !
b1011 +
18
0;
0.
15
b110 $
b110 *
b110 '
#870
1@
1B
1C
1>
17
08
1;
16
b111 ,
1/
b1100 !
b1100 +
00
11
1.
b111 $
b111 *
b111 '
#880
0F
0?
0B
06
0>
0/
b0 ,
07
0"
10
01
08
0;
1@
0A
0C
b1101 !
b1101 +
1G
0J
0.
05
0=
1E
b1000 $
b1000 *
b1000 '
#890
18
16
b1 ,
1/
b1110 !
b1110 +
00
11
1.
b1001 $
b1001 *
b1001 '
#900
0"
1G
0J
0F
0?
1@
0B
06
0>
0/
b0 ,
07
10
01
b1111 !
b1111 +
18
0;
0.
15
b1010 $
b1010 *
b1010 '
#910
1"
0G
1J
1F
1?
0@
1B
1>
17
08
1;
16
b111 ,
1/
b0 !
b0 +
00
11
1.
b1011 $
b1011 *
b1011 '
#920
0B
06
0>
0/
b100 ,
07
10
01
08
0;
b1 !
b1 +
0@
1A
0C
0.
05
1=
b1100 $
b1100 *
b1100 '
#930
18
16
b101 ,
1/
b10 !
b10 +
00
11
1.
b1101 $
b1101 *
b1101 '
#940
0@
0B
0C
06
0>
0/
b100 ,
07
10
01
b11 !
b11 +
18
0;
0.
15
b1110 $
b1110 *
b1110 '
#950
1@
1B
1C
1>
17
08
1;
16
b111 ,
1/
b100 !
b100 +
00
11
1.
b1111 $
b1111 *
b1111 '
#960
0F
0?
0B
0>
07
18
06
0"
b0 ,
0/
0;
1@
0A
0C
b110 !
b110 +
0G
0J
01
0:
0.
05
0=
0E
0-
14
b0 $
b0 *
b110 #
b110 )
b110 &
b0 '
#970
b111 !
b111 +
10
1.
b1 $
b1 *
b1 '
#980
1G
1F
1?
0@
1B
1>
b110 ,
17
00
b1000 !
b1000 +
08
19
0.
15
b10 $
b10 *
b10 '
#990
b1001 !
b1001 +
10
1.
b11 $
b11 *
b11 '
#1000
0B
0>
b100 ,
07
00
18
09
b1010 !
b1010 +
0@
1A
0C
0.
05
1=
b100 $
b100 *
b100 '
#1010
b1011 !
b1011 +
10
1.
b101 $
b101 *
b101 '
#1020
1@
1B
1C
1>
b110 ,
17
00
b1100 !
b1100 +
08
19
0.
15
b110 $
b110 *
b110 '
#1030
b1101 !
b1101 +
10
1.
b111 $
b111 *
b111 '
#1040
0F
0?
0B
0>
b0 ,
07
0"
00
18
09
1@
0A
0C
b1110 !
b1110 +
1G
0J
0.
05
0=
1E
b1000 $
b1000 *
b1000 '
#1050
b1111 !
b1111 +
10
1.
b1001 $
b1001 *
b1001 '
#1060
1"
0G
1J
1F
1?
0@
1B
1>
b110 ,
17
00
b0 !
b0 +
08
19
0.
15
b1010 $
b1010 *
b1010 '
#1070
b1 !
b1 +
10
1.
b1011 $
b1011 *
b1011 '
#1080
0B
0>
b100 ,
07
00
18
09
b10 !
b10 +
0@
1A
0C
0.
05
1=
b1100 $
b1100 *
b1100 '
#1090
b11 !
b11 +
10
1.
b1101 $
b1101 *
b1101 '
#1100
1@
1B
1C
1>
b110 ,
17
00
b100 !
b100 +
08
19
0.
15
b1110 $
b1110 *
b1110 '
#1110
b101 !
b101 +
10
1.
b1111 $
b1111 *
b1111 '
#1120
0F
0?
0B
0>
b0 ,
07
0"
18
09
1@
0A
0C
b111 !
b111 +
0G
0J
0.
05
0=
0E
1-
b0 $
b0 *
b111 #
b111 )
b111 &
b0 '
#1130
1G
1F
1?
0@
1B
1>
17
08
1:
16
b111 ,
1/
b1000 !
b1000 +
00
11
1.
b1 $
b1 *
b1 '
#1140
0:
06
b110 ,
0/
10
01
b1001 !
b1001 +
08
19
0;
0.
15
b10 $
b10 *
b10 '
#1150
18
1:
1;
16
b111 ,
1/
b1010 !
b1010 +
00
11
1.
b11 $
b11 *
b11 '
#1160
0B
0>
07
0:
06
b100 ,
0/
10
01
18
09
0;
b1011 !
b1011 +
0@
1A
0C
0.
05
1=
b100 $
b100 *
b100 '
#1170
1@
1B
1C
1>
17
08
1:
16
b111 ,
1/
b1100 !
b1100 +
00
11
1.
b101 $
b101 *
b101 '
#1180
0:
06
b110 ,
0/
10
01
b1101 !
b1101 +
08
19
0;
0.
15
b110 $
b110 *
b110 '
#1190
18
1:
1;
16
b111 ,
1/
b1110 !
b1110 +
00
11
1.
b111 $
b111 *
b111 '
#1200
0F
0?
0B
0>
07
0:
06
b0 ,
0/
0"
10
01
18
09
0;
1@
0A
0C
b1111 !
b1111 +
1G
0J
0.
05
0=
1E
b1000 $
b1000 *
b1000 '
#1210
1"
0G
1J
1F
1?
0@
1B
1>
17
08
1:
16
b111 ,
1/
b0 !
b0 +
00
11
1.
b1001 $
b1001 *
b1001 '
#1220
0:
06
b110 ,
0/
10
01
b1 !
b1 +
08
19
0;
0.
15
b1010 $
b1010 *
b1010 '
#1230
18
1:
1;
16
b111 ,
1/
b10 !
b10 +
00
11
1.
b1011 $
b1011 *
b1011 '
#1240
0B
0>
07
0:
06
b100 ,
0/
10
01
18
09
0;
b11 !
b11 +
0@
1A
0C
0.
05
1=
b1100 $
b1100 *
b1100 '
#1250
1@
1B
1C
1>
17
08
1:
16
b111 ,
1/
b100 !
b100 +
00
11
1.
b1101 $
b1101 *
b1101 '
#1260
0:
06
b110 ,
0/
10
01
b101 !
b101 +
08
19
0;
0.
15
b1110 $
b1110 *
b1110 '
#1270
18
1:
1;
16
b111 ,
1/
b110 !
b110 +
00
11
1.
b1111 $
b1111 *
b1111 '
#1280
0"
08
0@
b1000 !
b1000 +
1G
06
0>
0F
0/
07
b0 ,
0?
0;
0C
0J
01
09
0:
0A
0B
0I
0.
05
0=
0E
0-
04
0<
1D
b0 $
b0 *
b1000 #
b1000 )
b1000 &
b0 '
#1290
b1001 !
b1001 +
10
1.
b1 $
b1 *
b1 '
#1300
00
b1010 !
b1010 +
18
0.
15
b10 $
b10 *
b10 '
#1310
b1011 !
b1011 +
10
1.
b11 $
b11 *
b11 '
#1320
00
08
b1100 !
b1100 +
1@
0.
05
1=
b100 $
b100 *
b100 '
#1330
b1101 !
b1101 +
10
1.
b101 $
b101 *
b101 '
#1340
00
b1110 !
b1110 +
18
0.
15
b110 $
b110 *
b110 '
#1350
b1111 !
b1111 +
10
1.
b111 $
b111 *
b111 '
#1360
1"
00
08
0@
b0 !
b0 +
0G
1H
0.
05
0=
1E
b1000 $
b1000 *
b1000 '
#1370
b1 !
b1 +
10
1.
b1001 $
b1001 *
b1001 '
#1380
00
b10 !
b10 +
18
0.
15
b1010 $
b1010 *
b1010 '
#1390
b11 !
b11 +
10
1.
b1011 $
b1011 *
b1011 '
#1400
00
08
b100 !
b100 +
1@
0.
05
1=
b1100 $
b1100 *
b1100 '
#1410
b101 !
b101 +
10
1.
b1101 $
b1101 *
b1101 '
#1420
00
b110 !
b110 +
18
0.
15
b1110 $
b1110 *
b1110 '
#1430
b111 !
b111 +
10
1.
b1111 $
b1111 *
b1111 '
#1440
0"
08
0@
b1001 !
b1001 +
1G
0H
0.
05
0=
0E
1-
b0 $
b0 *
b1001 #
b1001 )
b1001 &
b0 '
#1450
18
16
b1 ,
1/
b1010 !
b1010 +
00
11
1.
b1 $
b1 *
b1 '
#1460
0@
06
0>
0/
b0 ,
07
10
01
b1011 !
b1011 +
18
0;
0.
15
b10 $
b10 *
b10 '
#1470
1@
1>
17
08
1;
16
b11 ,
1/
b1100 !
b1100 +
00
11
1.
b11 $
b11 *
b11 '
#1480
0"
1G
0I
06
0>
0F
0/
07
b0 ,
0?
10
01
08
0;
b1101 !
b1101 +
1@
0C
0.
05
1=
b100 $
b100 *
b100 '
#1490
18
16
b1 ,
1/
b1110 !
b1110 +
00
11
1.
b101 $
b101 *
b101 '
#1500
0"
1G
0I
0F
0?
1@
0C
06
0>
0/
b0 ,
07
10
01
b1111 !
b1111 +
18
0;
0.
15
b110 $
b110 *
b110 '
#1510
1"
0G
1I
1F
1?
0@
1C
1>
17
08
1;
16
b111 ,
1/
b0 !
b0 +
00
11
1.
b111 $
b111 *
b111 '
#1520
0I
06
0>
0F
0/
07
b0 ,
0?
10
01
08
0;
0@
0C
b1 !
b1 +
0G
1H
0J
0.
05
0=
1E
b1000 $
b1000 *
b1000 '
#1530
18
16
b1 ,
1/
b10 !
b10 +
00
11
1.
b1001 $
b1001 *
b1001 '
#1540
0@
06
0>
0/
b0 ,
07
10
01
b11 !
b11 +
18
0;
0.
15
b1010 $
b1010 *
b1010 '
#1550
1@
1>
17
08
1;
16
b11 ,
1/
b100 !
b100 +
00
11
1.
b1011 $
b1011 *
b1011 '
#1560
0G
0I
0J
06
0>
0F
0/
07
b0 ,
0?
10
01
08
0;
b101 !
b101 +
1@
0C
0.
05
1=
b1100 $
b1100 *
b1100 '
#1570
18
16
b1 ,
1/
b110 !
b110 +
00
11
1.
b1101 $
b1101 *
b1101 '
#1580
0G
0I
0J
0F
0?
1@
0C
06
0>
0/
b0 ,
07
10
01
b111 !
b111 +
18
0;
0.
15
b1110 $
b1110 *
b1110 '
#1590
1G
1I
1J
1F
1?
0@
1C
1>
17
08
1;
16
b111 ,
1/
b1000 !
b1000 +
00
11
1.
b1111 $
b1111 *
b1111 '
#1600
0>
0"
07
0I
18
0F
06
0?
b0 ,
0/
0;
0@
0C
b1010 !
b1010 +
1G
0H
0J
01
0:
0.
05
0=
0E
0-
14
b0 $
b0 *
b1010 #
b1010 )
b1010 &
b0 '
#1610
b1011 !
b1011 +
10
1.
b1 $
b1 *
b1 '
#1620
1@
1>
b10 ,
17
00
b1100 !
b1100 +
08
19
0.
15
b10 $
b10 *
b10 '
#1630
b1101 !
b1101 +
10
1.
b11 $
b11 *
b11 '
#1640
0"
1G
0I
0>
0F
07
b0 ,
0?
00
18
09
b1110 !
b1110 +
1@
0C
0.
05
1=
b100 $
b100 *
b100 '
#1650
b1111 !
b1111 +
10
1.
b101 $
b101 *
b101 '
#1660
1"
0G
1I
1F
1?
0@
1C
1>
b110 ,
17
00
b0 !
b0 +
08
19
0.
15
b110 $
b110 *
b110 '
#1670
b1 !
b1 +
10
1.
b111 $
b111 *
b111 '
#1680
0I
0>
0F
07
b0 ,
0?
00
18
09
0@
0C
b10 !
b10 +
0G
1H
0J
0.
05
0=
1E
b1000 $
b1000 *
b1000 '
#1690
b11 !
b11 +
10
1.
b1001 $
b1001 *
b1001 '
#1700
1@
1>
b10 ,
17
00
b100 !
b100 +
08
19
0.
15
b1010 $
b1010 *
b1010 '
#1710
b101 !
b101 +
10
1.
b1011 $
b1011 *
b1011 '
#1720
0G
0I
0J
0>
0F
07
b0 ,
0?
00
18
09
b110 !
b110 +
1@
0C
0.
05
1=
b1100 $
b1100 *
b1100 '
#1730
b111 !
b111 +
10
1.
b1101 $
b1101 *
b1101 '
#1740
1G
1I
1J
1F
1?
0@
1C
1>
b110 ,
17
00
b1000 !
b1000 +
08
19
0.
15
b1110 $
b1110 *
b1110 '
#1750
b1001 !
b1001 +
10
1.
b1111 $
b1111 *
b1111 '
#1760
0"
0I
0>
0F
07
b0 ,
0?
18
09
0@
0C
b1011 !
b1011 +
1G
0H
0J
0.
05
0=
0E
1-
b0 $
b0 *
b1011 #
b1011 )
b1011 &
b0 '
#1770
1@
1>
17
08
1:
16
b11 ,
1/
b1100 !
b1100 +
00
11
1.
b1 $
b1 *
b1 '
#1780
0:
06
b10 ,
0/
10
01
b1101 !
b1101 +
08
19
0;
0.
15
b10 $
b10 *
b10 '
#1790
18
1:
1;
16
b11 ,
1/
b1110 !
b1110 +
00
11
1.
b11 $
b11 *
b11 '
#1800
0>
07
0"
0:
1G
0I
06
0F
0/
b0 ,
0?
10
01
18
09
0;
b1111 !
b1111 +
1@
0C
0.
05
1=
b100 $
b100 *
b100 '
#1810
1"
0G
1I
1F
1?
0@
1C
1>
17
08
1:
16
b111 ,
1/
b0 !
b0 +
00
11
1.
b101 $
b101 *
b101 '
#1820
0:
06
b110 ,
0/
10
01
b1 !
b1 +
08
19
0;
0.
15
b110 $
b110 *
b110 '
#1830
18
1:
1;
16
b111 ,
1/
b10 !
b10 +
00
11
1.
b111 $
b111 *
b111 '
#1840
0>
07
0:
0I
06
0F
0/
b0 ,
0?
10
01
18
09
0;
0@
0C
b11 !
b11 +
0G
1H
0J
0.
05
0=
1E
b1000 $
b1000 *
b1000 '
#1850
1@
1>
17
08
1:
16
b11 ,
1/
b100 !
b100 +
00
11
1.
b1001 $
b1001 *
b1001 '
#1860
0:
06
b10 ,
0/
10
01
b101 !
b101 +
08
19
0;
0.
15
b1010 $
b1010 *
b1010 '
#1870
18
1:
1;
16
b11 ,
1/
b110 !
b110 +
00
11
1.
b1011 $
b1011 *
b1011 '
#1880
0>
07
0:
0G
0I
0J
06
0F
0/
b0 ,
0?
10
01
18
09
0;
b111 !
b111 +
1@
0C
0.
05
1=
b1100 $
b1100 *
b1100 '
#1890
1G
1I
1J
1F
1?
0@
1C
1>
17
08
1:
16
b111 ,
1/
b1000 !
b1000 +
00
11
1.
b1101 $
b1101 *
b1101 '
#1900
0:
06
b110 ,
0/
10
01
b1001 !
b1001 +
08
19
0;
0.
15
b1110 $
b1110 *
b1110 '
#1910
18
1:
1;
16
b111 ,
1/
b1010 !
b1010 +
00
11
1.
b1111 $
b1111 *
b1111 '
#1920
0"
0I
0F
0?
08
1@
06
0>
0/
b0 ,
07
0;
0C
b1100 !
b1100 +
1G
0H
0J
01
09
0:
0B
0.
05
0=
0E
0-
04
1<
b0 $
b0 *
b1100 #
b1100 )
b1100 &
b0 '
#1930
b1101 !
b1101 +
10
1.
b1 $
b1 *
b1 '
#1940
00
b1110 !
b1110 +
18
0.
15
b10 $
b10 *
b10 '
#1950
b1111 !
b1111 +
10
1.
b11 $
b11 *
b11 '
#1960
1"
0G
1I
1F
b100 ,
1?
00
08
b0 !
b0 +
0@
1A
0.
05
1=
b100 $
b100 *
b100 '
#1970
b1 !
b1 +
10
1.
b101 $
b101 *
b101 '
#1980
00
b10 !
b10 +
18
0.
15
b110 $
b110 *
b110 '
#1990
b11 !
b11 +
10
1.
b111 $
b111 *
b111 '
#2000
0I
0F
b0 ,
0?
00
08
1@
0A
b100 !
b100 +
0G
1H
0J
0.
05
0=
1E
b1000 $
b1000 *
b1000 '
#2010
b101 !
b101 +
10
1.
b1001 $
b1001 *
b1001 '
#2020
00
b110 !
b110 +
18
0.
15
b1010 $
b1010 *
b1010 '
#2030
b111 !
b111 +
10
1.
b1011 $
b1011 *
b1011 '
#2040
1G
1I
1J
1F
b100 ,
1?
00
08
b1000 !
b1000 +
0@
1A
0.
05
1=
b1100 $
b1100 *
b1100 '
#2050
b1001 !
b1001 +
10
1.
b1101 $
b1101 *
b1101 '
#2060
00
b1010 !
b1010 +
18
0.
15
b1110 $
b1110 *
b1110 '
#2070
b1011 !
b1011 +
10
1.
b1111 $
b1111 *
b1111 '
#2080
0"
0I
0F
b0 ,
0?
08
1@
0A
b1101 !
b1101 +
1G
0H
0J
0.
05
0=
0E
1-
b0 $
b0 *
b1101 #
b1101 )
b1101 &
b0 '
#2090
18
16
b1 ,
1/
b1110 !
b1110 +
00
11
1.
b1 $
b1 *
b1 '
#2100
0"
1G
0I
0F
0?
1@
0B
06
0>
0/
b0 ,
07
10
01
b1111 !
b1111 +
18
0;
0.
15
b10 $
b10 *
b10 '
#2110
1"
0G
1I
1F
1?
0@
1B
1>
17
08
1;
16
b111 ,
1/
b0 !
b0 +
00
11
1.
b11 $
b11 *
b11 '
#2120
0B
06
0>
0/
b100 ,
07
10
01
08
0;
b1 !
b1 +
0@
1A
0C
0.
05
1=
b100 $
b100 *
b100 '
#2130
18
16
b101 ,
1/
b10 !
b10 +
00
11
1.
b101 $
b101 *
b101 '
#2140
0@
0B
0C
06
0>
0/
b100 ,
07
10
01
b11 !
b11 +
18
0;
0.
15
b110 $
b110 *
b110 '
#2150
1@
1B
1C
1>
17
08
1;
16
b111 ,
1/
b100 !
b100 +
00
11
1.
b111 $
b111 *
b111 '
#2160
0I
0F
0?
0B
06
0>
0/
b0 ,
07
10
01
08
0;
1@
0A
0C
b101 !
b101 +
0G
1H
0J
0.
05
0=
1E
b1000 $
b1000 *
b1000 '
#2170
18
16
b1 ,
1/
b110 !
b110 +
00
11
1.
b1001 $
b1001 *
b1001 '
#2180
0G
0I
0J
0F
0?
1@
0B
06
0>
0/
b0 ,
07
10
01
b111 !
b111 +
18
0;
0.
15
b1010 $
b1010 *
b1010 '
#2190
1G
1I
1J
1F
1?
0@
1B
1>
17
08
1;
16
b111 ,
1/
b1000 !
b1000 +
00
11
1.
b1011 $
b1011 *
b1011 '
#2200
0B
06
0>
0/
b100 ,
07
10
01
08
0;
b1001 !
b1001 +
0@
1A
0C
0.
05
1=
b1100 $
b1100 *
b1100 '
