Adders/adder_subtractor/full_adder.v
module full_adder(
input A, B, C,
output Sum, Carry);

wire a1,a2,a3;

xor(Sum,A,B,C);
and(a1,A,B);
and(a2,A,C);
and(a3,C,B);
or(Carry,a1,a2,a3);
endmodule

Adders/full_Adder/full_adder_tb.v
module full_adder_tb;
reg a,b,c;
wire sum,carry;
integer i;
full_adder dut(
.A(a),
.B(b),
.C(c),
.Sum(sum),
.Carry(carry));

initial begin

$dumpfile("full_adder.vcd");
$dumpvars(0,full_adder_tb);

for(i=0; i<8; i=i+1) begin
{a,b,c}=i;
#10;
end
$finish ;
end
initial begin
$monitor("A=%b,B=%b,C=%b,Sum=%b,Carry=%b",a,b,c,sum,carry);
end
endmodule

Adders/full_Adder/full_adder.vcd
$date
	Fri Jun 19 05:23:16 2026
$end
$version
	Icarus Verilog
$end
$timescale
	1s
$end
$scope module full_adder_tb $end
$var wire 1 ! sum $end
$var wire 1 " carry $end
$var reg 1 # a $end
$var reg 1 $ b $end
$var reg 1 % c $end
$var integer 32 & i [31:0] $end
$scope module dut $end
$var wire 1 # A $end
$var wire 1 $ B $end
$var wire 1 % C $end
$var wire 1 " Carry $end
$var wire 1 ! Sum $end
$var wire 1 ' a1 $end
$var wire 1 ( a2 $end
$var wire 1 ) a3 $end
$upscope $end
$upscope $end
$enddefinitions $end
$comment Show the parameter values. $end
$dumpall
$end
#0
$dumpvars
0)
0(
0'
b0 &
0%
0$
0#
0"
0!
$end
#10
1!
1%
b1 &
#20
1$
0%
b10 &
#30
1"
0!
1)
1%
b11 &
#40
0"
1!
0)
1#
0$
0%
b100 &
#50
1"
0!
1(
1%
b101 &
#60
1'
0(
1$
0%
b110 &
#70
1!
1(
1)
1%
b111 &
#80
b1000 &
